{
 "version": {
  "label": "4th",
  "year": 2002,
  "publisher": "Pearson",
  "matches_pref": true
 },
 "sol_alignment": null,
 "confidence": "high",
 "evidence": [
  "z-lib 28217619：Friedberg/Insel/Spence Linear Algebra 4th 2002 Pearson, 624pp；作者三人鎖定排除 Hoffman-Kunze/Lang/Strang；非 Elementary Linear Algebra 別系列"
 ],
 "sources": [
  {
   "note": "zlib_detail:28217619/1c350b"
  },
  {
   "note": "web:editions"
  }
 ],
 "by": "restock",
 "checked_at": "2026-06-22T01:23:29+00:00",
 "identity": null,
 "classification": {
  "field_id": "undergrad_foundations",
  "subject": "線性代數"
 },
 "qualification": {
  "eligible": true,
  "verified_at": "2026-06-22T01:23:29+00:00"
 }
}