{
 "version": {
  "label": "6th ed.",
  "year": 2011,
  "matches_pref": true
 },
 "sol_alignment": null,
 "confidence": "high",
 "evidence": [
  "W.H. Freeman 2011, Marsden & Tromba, 578pp, advisory_conf=1.0"
 ],
 "sources": [
  {
   "note": "zlib_detail:29926522/452e13"
  }
 ],
 "by": "restock",
 "checked_at": "2026-06-24T12:37:56+00:00",
 "identity": {
  "title": "Vector Calculus",
  "author": "Marsden & Tromba",
  "edition_pref": "",
  "has_solution": false,
  "promoted_from": "discovered"
 },
 "classification": {
  "field_id": "undergrad_foundations",
  "subject": "向量微積分"
 },
 "qualification": {
  "eligible": true,
  "verified_at": "2026-06-24T12:17:47+00:00"
 }
}