{
 "version": {
  "label": "1st Edition",
  "year": 2003,
  "matches_pref": true
 },
 "sol_alignment": null,
 "confidence": "high",
 "evidence": [
  "Razavi Design of Analog CMOS 1st ed, McGraw-Hill, 694 pages, advisory_conf=1.0"
 ],
 "sources": [
  {
   "note": "zlib_detail:464544/d093ae"
  }
 ],
 "by": "restock",
 "checked_at": "2026-06-24T13:23:19+00:00",
 "identity": {
  "title": "Design of Analog CMOS Integrated Circuits",
  "author": "Behzad Razavi",
  "edition_pref": "",
  "has_solution": false,
  "promoted_from": "discovered"
 },
 "classification": {
  "field_id": "ee",
  "subject": "類比積體電路"
 },
 "qualification": {
  "eligible": true,
  "verified_at": "2026-06-24T13:15:14+00:00"
 }
}