{
  "title": "熱力學第三定律",
  "body": [
    {
      "i": 0,
      "md": "18.1 熱力學第三定律的不同表述 193"
    },
    {
      "i": 1,
      "md": "18.2 熱力學第三定律的推論 195"
    },
    {
      "i": 2,
      "md": "章節摘要 198"
    },
    {
      "i": 3,
      "md": "習題 198"
    },
    {
      "i": 4,
      "caption": "Fig. 18.1 方程式 18.3 的圖形表示。"
    },
    {
      "i": 6,
      "caption": "Fig. 18.2 W. Nernst   Fig. 18.3 M. Planck"
    },
    {
      "i": 7,
      "md": "$G = H - T S$ ，我們預期"
    },
    {
      "i": 9,
      "md": "使得當 $T \\to 0$ 時，$\\Delta G \\to \\Delta H$。實驗數據顯示這確實成立，但 $\\Delta G$ 與 $\\Delta H$ 不僅在降溫時彼此接近，而且是漸近地趨近。根據這些數據，Nernst 進一步假設：當 $T  0$ 時，$\\Delta S  0$。他在 1906 年對第三定律的表述可以寫為"
    },
    {
      "i": 10,
      "md": "Nernst 的第三定律表述"
    },
    {
      "i": 11,
      "md": "在絕對零度附近，處於內部平衡的系統中所有反應都以不改變熵的方式進行。"
    },
    {
      "i": 12,
      "md": "Max Planck（1858–1947）（Fig. 18.3）在 1911 年進一步充實了這一表述，提出了如下假設："
    },
    {
      "i": 13,
      "md": "Planck 的第三定律表述"
    },
    {
      "i": 14,
      "md": "所有處於內部平衡的系統，在絕對零度時的熵相同，且可取為零。"
    },
    {
      "i": 15,
      "md": "Planck 原本的表述僅針對完美晶體。然而，普遍認為這對任何系統都成立，只要系統處於內部平衡（即系統各部分互相達到平衡）。有些系統，例如 $^ { 4 } \\mathrm { H e }$ 和 $^ { 3 } \\mathrm { H e }$，即使在極低溫下仍是液態。金屬中的電子可以被視為一種氣體，一直延伸到 $T = 0$。第三定律適用於所有這些系統。然而，請注意，第三定律適用的前提是系統處於內部平衡。一個未處於平衡的例子是玻璃，其中存在凍結的無序。對於固體而言，最低能量的相是完美晶體，但玻璃相的能量較高且不穩定。玻璃相最終會弛豫回完美晶體相，但這可能需要數年乃至數個世紀。"
    },
    {
      "i": 16,
      "md": "Planck 選擇以零作為熵的基準，進一步受到統計力學發展的啟發，這一學科我們將在本書後續部分加以探討。在此僅需說明：統計力學對熵的定義，即方程式 14.36 中的 $( S = k _ { \\mathrm { B } } \\ln \\Omega )$，意味著零熵等價於 $\\Omega = 1$。因此，在絕對零度時，當系統進入基態，熵為零意味著該基態是非簡併的。"
    },
    {
      "i": 17,
      "md": "此時，我們可以對 Planck 形式的第三定律提出一個潛在的異議。考慮一個由 N 個無自旋原子組成的完美晶體。第三定律告訴我們其熵為零。然而，進一步假設每個原子的核心有一個角動量量子數為 I 的原子核。若對此系統不施加磁場，則似乎出現了矛盾。核自旋的簡併度為 $2 I + 1$，若 $I > 0$，則簡併度不等於一。如何協調這與零熵之間的矛盾？因為非零的核自旋意味著無論冷卻到多低的溫度，此系統的熵 S 都應為 $S = N k _ { \\mathrm { B } } \\ln ( 2 I + 1 )$。"
    },
    {
      "i": 18,
      "md": "這一表觀矛盾的解答如下：在真實的處於內部平衡的系統中，系統的各個組成部分必須能夠彼此交換能量，即互相相互作用。核自旋實際上受到彼此偶極場產生的微弱但非零的磁場作用，這解除了簡併。另一種理解方式是：相互作用產生核自旋的集體激發，即核自旋波，而最低能量的核自旋波——對應最長波長的模式——是非簡併的。在足夠低的溫度下（這將是極低的溫度！），只有該長波長模式會被熱佔據，核自旋系統的熵將為零。"
    },
    {
      "i": 19,
      "md": "然而，這個例子提出了一個重要問題。若我們冷卻晶體，將從晶格中抽取能量，其熵將趨向零。但核自旋仍會保有其熵，直至冷卻到更低的溫度（反映核自旋之間的相互作用相較於晶格中原子間的鍵結更為微弱）。若我們找到冷卻原子核的方法，與個別核子相關的殘餘熵可能仍然存在。所有這些熱力學子系統（電子、核自旋和核子）之間的耦合非常微弱，但其熵是可加的。Francis Simon（1893–1956）（Fig. 18.4）在 1937 年將這些不同的子系統稱為「面向」（aspects），並如下表述第三定律："
    },
    {
      "i": 20,
      "md": "Simon 的第三定律表述"
    },
    {
      "i": 21,
      "md": "系統中每個處於內部熱力學平衡的面向對系統熵的貢獻，在 $T  0$ 時趨向零。"
    },
    {
      "i": 22,
      "md": "Simon 的表述很便利，因為它允許我們專注於某個感興趣的面向，知道其熵在 T 趨近 0 時將趨向零，同時忽略那些我們不關心、且可能直到更接近 $T = 0$ 才失去熵的面向。"
    },
    {
      "i": 23,
      "title": "熱力學第三定律的推論"
    },
    {
      "i": 24,
      "md": "在提供了第三定律的各種表述之後，現在是時候探討其一些推論。"
    },
    {
      "i": 25,
      "md": "• 熱容在 $T  0$ 時趨向零"
    },
    {
      "i": 26,
      "md": "這一推論很容易證明。任何熱容 C 由下式給出"
    },
    {
      "i": 28,
      "caption": "Fig. 18.4 F. E. Simon"
    },
    {
      "i": 29,
      "md": "因為當 $T  0$ 時，ln $T \\to - \\infty$ 且 $S \\to 0$。因此 $C  0$。"
    },
    {
      "i": 30,
      "md": "注意，這一結果與古典預測（每莫耳每個自由度 $C =$ $R / 2$）不一致。（我們在此順帶指出：這一觀察強調了能量均分定理——將在 Chapter 19 介紹——是一個高溫理論，在低溫下失效。）"
    },
    {
      "i": 31,
      "md": "• 熱膨脹停止"
    },
    {
      "i": 32,
      "md": "由於 $T  0$ 時 $S \\to 0$，例如我們有"
    },
    {
      "i": 34,
      "md": "當 $T  0$ 時，但根據 Maxwell 關係，這意味著"
    },
    {
      "i": 36,
      "md": "因此等壓膨脹係數 $\\beta _ { p }  0$"
    },
    {
      "i": 37,
      "md": "• 氣體在 $T  0$ 時不再保持理想"
    },
    {
      "i": 38,
      "md": "理想單原子氣體在本書中作為一個簡單模型發揮了重要作用，使我們能夠得到易於處理的結果。其中一個結果是方程式 11.26，它指出對於理想氣體，每莫耳的 $C _ { p } - C _ { V } = R$。然而，當 $T  0$ 時，$C _ { p }$ 與 $C _ { V }$ 都趨向零，該方程式無法滿足。此外，我們預期每莫耳的 $C _ { V } = 3 R / 2$，正如我們所見，這在趨近絕對零度時也不成立。理想氣體的另一個問題是方程式 16.82 給出的熵表達式（$S = C _ { V }$ ln $T + R$ ln V + 常數）。當 $T  0$ 時，此方程式給出 $S \\to - \\infty$，這與零相去甚遠！"
    },
    {
      "i": 39,
      "md": "因此，我們看到第三定律迫使我們在思考低溫氣體時放棄理想氣體模型。當然，正是在低溫下，氣體分子之間的微弱相互作用（由於我們將氣體分子模型化為獨立個體而一直忽略）變得更為重要。更複雜的氣體模型將在 Chapter 26 中探討。"
    },
    {
      "i": 40,
      "md": "• Curie 定律失效"
    },
    {
      "i": 41,
      "md": "Curie 定律指出磁化率 χ 正比於 $1 / T$，因此當 $T  0$ 時 $\\chi \\to \\infty$。然而，第三定律意味著 $( \\partial S / \\partial B ) _ { T }  0$，從而"
    },
    {
      "i": 43,
      "md": "必須趨向零。因此 $\\begin{array} { r } { ( \\frac { \\partial \\chi } { \\partial T } )  0 , } \\end{array}$，這與 Curie 定律不符。為何它會失效？你可能已開始察覺一個主題：又是相互作用！Curie 定律是在磁矩完全獨立的假設下推導的，在這種情況下，其性質可通過僅考慮施加磁場（驅使磁矩對齊）的平衡來確定"
    },
    {
      "i": 44,
      "md": "與溫度（驅使磁矩隨機化）之間的平衡。磁化率衡量它們對無窮小外加磁場的無窮小響應；當 $T = 0$ 時熱漲落消失，這一響應變為無窮大。然而，若磁矩之間的相互作用被激活，外加磁場的效果將大為減弱，因為磁矩已被彼此驅入某種部分有序的狀態。"
    },
    {
      "i": 45,
      "md": "這裡有一個基本的深層訊息：在高溫下，當熱能 $k _ { \\mathrm { B } } T$ 遠大於任何相互作用能時，系統的微觀組成部分可以獨立行為。在低溫下，這些相互作用變得重要，所有獨立性的概念都會崩潰。借用（並不恰當地改寫）詩人 John Donne 的話："
    },
    {
      "i": 46,
      "md": "沒有人是一座孤島，尤其是在 $T  0$ 的時候。"
    },
    {
      "i": 47,
      "md": "絕對零度的不可達性"
    },
    {
      "i": 48,
      "md": "最後這一點幾乎可以提升為第三定律的另一種表述："
    },
    {
      "i": 49,
      "md": "不可能在有限步驟內將溫度冷卻至 $T = 0$。"
    },
    {
      "i": 50,
      "md": "嚴格證明這一點較為繁瑣，但我們可以參考 Fig. 18.5 來論證，該圖顯示了不同參數 X 值（例如磁場）下 S 對 T 的曲線。降溫通過 X 的等溫增加和 X 的絕熱減少來實現。若第三定律不成立，則可以按照 Fig. 18.5(a) 的方式冷卻一路到絕對零度。然而，由於第三定律的存在，情況如 Fig. 18.5(b) 所示，到達絕對零度所需的步驟數變為無窮。"
    },
    {
      "i": 51,
      "md": "在結束本章之前，我們就 Carnot 引擎作一點說明。考慮一個在溫度分別為 $T _ { \\ell }$ 和 $T _ { \\mathrm { h } }$ 的熱庫之間運行的 Carnot 引擎，其效率等於 $\\eta =$ $1 - ( T _ { \\ell } / T _ { \\mathrm { h } } )$（方程式 13.10）。若 $T _ { \\ell } \\to 0$，效率 η 趨近於 1。若你運行這個 Carnot 引擎，就能將熱完全轉化為功，這違反了熱力學第二定律的 Kelvin 表述。乍看之下，絕對零度的不可達性（第三定律的一個版本）似乎是第二定律的簡單推論。然而，考慮在兩個熱庫之間運行 Carnot 引擎——其中一個在絕對零度——存在困難。目前尚不清楚如何在絕對零度下執行等溫過程，因為一旦系統達到絕對零度，在不加熱的情況下無法改變其熱力學狀態。因此，普遍認為第三定律確實是一個獨立的公設，不依賴於第二定律。第三定律指出，我們許多「簡單」的熱力學模型——如理想氣體方程和順磁體的 Curie 定律——若要在 $T  0$ 時給出正確預測，需要進行實質性的修正。因此，適時探討基於真實系統微觀性質的更精密模型，這正是統計力學的內容，也是本書下一部分的主題。"
    },
    {
      "i": 52,
      "caption": "(a) (b)"
    },
    {
      "i": 53,
      "caption": "Fig. 18.5 不同參數 X 值下熵關於溫度的函數圖。降溫通過 X 的等溫增加（即 $X _ { 1 }  \\bar { X } _ { 2 }$）和 X 的絕熱減少（$X \\ ( \\mathrm { i . e . } \\ X _ { 2 } \\  \\ X _ { 1 } )$）來實現。(a) 若 $T  0$ 時 S 不趨向 0，則可以在有限步驟內冷卻至絕對零度。(b) 若遵循第三定律，則不可能在有限步驟內冷卻至絕對零度。"
    },
    {
      "i": 54,
      "md": "章節摘要"
    },
    {
      "i": 55,
      "md": "• 熱力學第三定律可以有多種表述：\n\n• Nernst：在絕對零度附近，處於內部平衡的系統中所有反應都以不改變熵的方式進行。\n\n• Planck：所有處於內部平衡的系統，在絕對零度時的熵相同，且可取為零。\n\nSimon：系統中每個處於內部熱力學平衡的面向對系統熵的貢獻，在 $T  0$ 時趨向零。\n\n• $T = 0$ 的不可達性：不可能在有限步驟內將溫度冷卻至 $T = 0$。\n\n• 第三定律意味著熱容與熱膨脹係數在 $T  0$ 時趨向零。\n\n• 在 $T  0$ 時，系統各組成部分之間的相互作用變得重要，導致理想氣體概念的崩潰以及 Curie 定律的失效。"
    }
  ],
  "problems": [
    {
      "num": "18.1",
      "body": [
        {
          "i": 0,
          "md": "總結熱力學第三定律的主要推論。解釋它如何對某些熱力學模型的結論投下懷疑的陰影。"
        }
      ]
    },
    {
      "num": "18.2",
      "body": [
        {
          "i": 0,
          "md": "回顧方程式 16.26，"
        },
        {
          "i": 2,
          "md": "從而證明"
        },
        {
          "i": 4,
          "md": "並解釋當 $T $ 0 時這些項會發生什麼。"
        },
        {
          "i": 5,
          "md": "第 VII 部分"
        },
        {
          "i": 6,
          "md": "統計力學"
        },
        {
          "i": 7,
          "md": "在這一部分，我們介紹統計力學。這是一個熱力學理論，以統計方式考慮個別原子或分子的微觀性質。統計力學允許從個別原子和分子微觀行為的統計分布中計算宏觀性質。本部分結構如下："
        },
        {
          "i": 8,
          "md": "• 在 Chapter 19 中，我們介紹能量均分定理，這一原理指出：由大量粒子組成的古典系統在熱平衡時，其內能將均勻分布於粒子可及的每個二次方自由度。\n\n• 在 Chapter 20 中，我們引入配分函數，它編碼了系統各態及其熱佔據的所有資訊。擁有配分函數便可計算系統的所有熱力學性質。\n\n• 在 Chapter 21 中，我們計算理想氣體的配分函數，並用其定義量子濃度。我們說明分子的不可分辨性如何影響統計性質並產生熱力學後果。\n\n• 在 Chapter 22 中，我們將配分函數的結果推廣到粒子數可變的系統，從而定義化學勢並引入巨配分函數。\n\n• 在 Chapter 23 中，我們考慮光的統計力學——光被量子化為光子——介紹黑體輻射、輻射壓力和宇宙微波背景。\n\n• 在 Chapter 24 中，我們討論晶格振動的類比行為——量子化為聲子——並介紹固體熱性質的 Einstein 模型和 Debye 模型。"
        }
      ]
    }
  ]
}