{
  "title": "狹義相對論力學",
  "body": [
    {
      "i": 0,
      "md": "5"
    },
    {
      "i": 1,
      "md": "Newton 力學定律必須加以修改，以符合前一章所介紹的狹義相對論原理。本章從四維時空的觀點描述狹義相對論力學。Newton 力學是狹義相對論力學的近似，適用於在特定慣性系中運動速度遠小於光速的情形。我們從四向量這一核心概念出發。"
    },
    {
      "i": 2,
      "title": "四向量"
    },
    {
      "i": 3,
      "md": "四向量定義為四維平坦時空中的有向線段，就如同三維向量（本章稱之為三向量）可定義為三維 Euclid 空間中的有向線段一樣。粗體字母表示四向量——例如 a——以區別於三向量，例如 $\\vec{a}$。本章將嚴格使用四向量與三向量的術語，但後續各章通常僅稱向量，並依上下文加以區別。"
    },
    {
      "i": 4,
      "caption": "FIGURE 5.1 四向量的加法與數乘。將四向量 a 與 b 平行移動直至它們在右側構成三角形，即可完成加法。和 $a + b$ 是從第一個向量的尾到第二個向量的頭的有向線段。數 $\\alpha$ 乘以四向量，得到方向相同、長度為原來 $\\alpha$ 倍的四向量。$^{1}$"
    },
    {
      "i": 5,
      "md": "$^{1}$ 對於長度為零的零四向量，先將其寫成兩個長度非零的四向量之和，再分別乘以 $\\alpha$，然後求和。"
    },
    {
      "i": 6,
      "caption": "FIGURE 5.2 類時、類空與零四向量。三種四向量分別指向時空中的類時、類空與零方向；參見 Figure 4.9。注意，零四向量在時空的非 Euclid 幾何中長度為零。"
    },
    {
      "i": 7,
      "caption": "FIGURE 5.3 沿座標軸方向的基底四向量。"
    },
    {
      "i": 8,
      "caption": "FIGURE 5.4 四向量 a 可由其沿座標軸方向的分量 $(a^{t}, a^{x}, a^{y}, a^{z})$ 來表示。"
    },
    {
      "i": 9,
      "md": "四向量可按向量的通常規則進行數乘、加法與減法（見 Figure 5.1）。四向量的長度是其尾與頭之間時空距離的絕對值。尾與頭具有類空間隔的四向量稱為類空四向量；具有類時間隔的稱為類時四向量；具有零間隔的稱為零四向量。零四向量的長度為零。不同類型的例子見 Figure 5.2。"
    },
    {
      "i": 10,
      "md": "上述四向量的定義，以及加法、數乘與計算長度的規則，均不涉及任何特定慣性系。它們是不變的——在所有慣性系中形式相同。當力學定律用四向量表述時，它們在每個慣性系中必然具有相同的形式，其預測結果也與相對性原理一致。這正是四向量的用途與重要性所在。"
    },
    {
      "i": 11,
      "md": "基底四向量與分量"
    },
    {
      "i": 12,
      "md": "在特定慣性系中，可引入沿 t、x、y、z 座標軸方向的單位長度基底四向量，如 Figure 5.3 所示。我們稱這些基底四向量為 $e_{t}$、$e_{x}$、$e_{y}$、$e_{z}$，或等價地，$e_{0}$、$e_{1}$、$e_{2}$、$e_{3}$，其中 0 代表 t，1 代表 x，以此類推。這四個四向量合在一起稱為四向量的基底，因為任何四向量都可以表示為它們的線性組合，如 Figure 5.4 所示："
    },
    {
      "i": 14,
      "md": "數組 $(a^t, a^x, a^y, a^z)$——或等價地，$(a^0, a^1, a^2, a^3)$——稱為四向量的分量。$^{2}$ 分量的標記始終寫作上標。$^{3}$"
    },
    {
      "i": 15,
      "md": "還有一些書寫 (5.1) 的其他有用方式，例如"
    },
    {
      "i": 17,
      "md": "或等價地，"
    },
    {
      "i": 19,
      "md": "若引入求和約定，即在任何表達式中，重複的上下標指標默認對其求和，則 (5.3) 式可以寫得更加緊湊。希臘字母指標從 0 加到 3；羅馬字母指標從 1 加到 3。因此，"
    },
    {
      "i": 21,
      "md": "與 (5.3) 相同。類似地，對於三向量，"
    },
    {
      "i": 23,
      "md": "其中 $\\vec{e}_i$，$i = 1, 2, 3$ 與 $(\\mathbf{e}_1, \\mathbf{e}_2, \\mathbf{e}_3)$ 相同。任何重複指標均表示求和，因此 (5.4) 也可以寫成"
    },
    {
      "i": 25,
      "md": "重複指標因此稱為啞指標或求和指標。關於求和約定的規則，我們在 Section 7.3 中有更多說明。"
    },
    {
      "i": 26,
      "md": "給定四向量的分量與基底四向量，等價於給定四向量本身。列出分量有多種有用的方式，即"
    },
    {
      "i": 28,
      "md": "Example 5.1. 位移四向量。四向量的一個簡單例子是兩個事件 $A$ 與 $B$ 之間的位移四向量 $\\Delta x$，例如 Figure 5.5 中所示的那些事件。"
    },
    {
      "i": 29,
      "md": "若 $(t_A, x_A, y_A, z_A)$ 是事件 $A$ 在特定慣性系中的座標，$(t_B, x_B, y_B, z_B)$ 是事件 $B$ 的座標，則它們之間的位移四向量 $\\Delta x$ 的分量為 $(t_B - t_A, x_B - x_A$，"
    },
    {
      "i": 30,
      "md": "具有一些數學背景的讀者可能知道，四向量的分量可以區分為不同種類。這種區別直到 Chapter 20 才會用到，在此之前我們僅使用此處定義的分量。\n\n現在你可能在想，手寫四向量方程時如何表示，因為電子排版之前的印刷指令是用波浪下劃線代替粗體。因此 (5.1) 可以寫成"
    },
    {
      "i": 32,
      "md": "四向量的分量"
    },
    {
      "i": 33,
      "md": "求和約定"
    },
    {
      "i": 34,
      "caption": "FIGURE 5.5 時空中兩點 A 與 B 之間的位移四向量 $\\Delta x$。"
    },
    {
      "i": 35,
      "md": "$y_{B} - y_{A}, z_{B} - z_{A}$。這可以用更緊湊的形式寫成"
    },
    {
      "i": 37,
      "md": "此表達式是四個方程的簡寫，$\\alpha$ 取每個值對應一個方程，$\\alpha = 0, 1, 2, 3$。指標 $\\alpha$ 稱為自由指標——「自由」地取 0 到 3 之間的任意值，每個值給出不同的方程。"
    },
    {
      "i": 38,
      "md": "四向量的分量在不同慣性系中各不相同，因為座標基底四向量不同。四向量——有向線段——的分量在慣性系之間的變換方式，與位移四向量的分量相同。例如，對於由 (4.21) 中沿 x 軸作勻速運動 v 相關聯的兩個慣性系，四向量 a 的分量的變換為"
    },
    {
      "i": 39,
      "md": "向量的 Lorentz 推進"
    },
    {
      "i": 44,
      "md": "（如果你在疑惑 (4.21) 中的 $c$ 因子去哪了，請記住在前一章末尾我們說過從此將使用 $c = 1$ 的單位制。）"
    },
    {
      "i": 45,
      "md": "純量積"
    },
    {
      "i": 46,
      "md": "純量積是四向量計算中的重要概念，正如它在三向量中一樣。兩個四向量 a 與 b 的純量積記為 $a \\cdot b$。它滿足純量積的通常數學規則："
    },
    {
      "i": 50,
      "md": "其中 a、b、c 是任意三個四向量，$\\alpha$ 是任意數。"
    },
    {
      "i": 51,
      "md": "若已知所有基底四向量對之間的純量積，則計算四向量的純量積很簡單，因為若 $a = a^{\\alpha}e_{\\alpha}$，$b = b^{\\beta}e_{\\beta}$，則"
    },
    {
      "i": 54,
      "md": "（此表達式中有雙重求和，一個對 $\\alpha$ 求和，另一個對 $\\beta$ 求和。）對於指向慣性系正交座標軸 $(t, x, y, z)$ 方向的基底四向量的純量積 $\\mathbf{e}_{\\alpha} \\cdot \\mathbf{e}_{\\beta}$，採用特殊記號："
    },
    {
      "i": 55,
      "md": "平坦時空的度規"
    },
    {
      "i": 57,
      "md": "從而 a · b 可以寫成"
    },
    {
      "i": 59,
      "md": "向量純量積"
    },
    {
      "i": 60,
      "md": "默認對 $\\alpha$ 與 $\\beta$ 進行雙重求和。一旦 $\\eta_{\\alpha \\beta}$ 已知，所有向量的純量積便完全確定。"
    },
    {
      "i": 61,
      "md": "$\\eta_{\\alpha\\beta}$ 由以下條件確定：位移四向量與自身的純量積給出它所連接兩點之間距離的平方："
    },
    {
      "i": 63,
      "md": "由純量積定義的四向量長度與定義為從尾到頭距離的長度一致。將此與 $(\\Delta s)^{2}$ 的 (4.6) 比較，並注意由 (5.12) 和 (5.10a) 可知 $\\eta_{\\alpha\\beta} = \\eta_{\\beta\\alpha}$，我們得到"
    },
    {
      "i": 65,
      "md": "此處 $\\eta_{\\alpha\\beta}$ 以對角對稱矩陣的形式顯示。鑑於 (5.14)，矩陣 $\\eta_{\\alpha\\beta}$ 可以與求和約定一起使用，以特別緊湊的形式表達平坦時空的線元 (4.8)："
    },
    {
      "i": 67,
      "md": "平坦時空的線元"
    },
    {
      "i": 68,
      "md": "在此意義下，$\\eta_{\\alpha\\beta}$ 稱為平坦時空的度規。"
    },
    {
      "i": 69,
      "md": "將 (5.15) 代入 (5.13)，可得兩個四向量 a 與 b 的純量積在慣性系中用其分量表示的以下完全等價的明顯形式："
    },
    {
      "i": 73,
      "md": "由於定義本身不涉及特定慣性系，純量積在所有慣性系中的值相同。在另一慣性系中，a 的分量為 $(a^{t'}, a^{\\lambda'}, a^{\\gamma'}, a^{z'})$，b 的分量為 $(b^{t^{\\prime}}, b^{x^{\\prime}}, b^{y^{\\prime}}, b^{z^{\\prime}})$，給出相同的數值 $\\mathbf{a} \\cdot \\mathbf{b}$："
    },
    {
      "i": 75,
      "md": "這由定義可得，但也可以從 (5.9) 明確驗證。"
    },
    {
      "i": 76,
      "md": "Example 5.2. Lorentz 推進保留座標軸的正交性。Figure 4.13 中的 $(t', x')$ 軸（現取 $c = 1$）在印刷頁面的幾何中看起來不正交，但在時空幾何中它們是正交的。為了在 $(t, x)$ 系中明確看到這一點，考慮沿 $t'$ 軸的單位位移四向量 $\\mathbf{a}$ 與沿 $x'$ 軸的單位位移四向量 $\\mathbf{b}$。這些四向量的 $(t', x', y', z')$ 分量分別為 $a^{\\alpha'} = (1, 0, 0, 0)$ 與 $b^{\\alpha'} = (0, 1, 0, 0)$。因此，由 (5.17) 在 $(t', x', y', z')$ 系中計算得 $\\mathbf{a} \\cdot \\mathbf{b} = 0$，這些四向量正交。這意味著它們在任何其他慣性系中也正交，但在 $(t, x, y, z)$ 系中明確計算很有啟發性。由 (5.9)，$(t, x, y, z)$ 分量為"
    },
    {
      "i": 78,
      "md": "再由 (5.17)，"
    },
    {
      "i": 80,
      "title": "狹義相對論運動學"
    },
    {
      "i": 81,
      "md": "引入了四向量的概念之後，我們現在轉而討論如何用四向量描述粒子在時空中的運動。這就是狹義相對論運動學的主題。"
    },
    {
      "i": 82,
      "md": "粒子沿時空中的類時世界線運動。在特定慣性系中，這條曲線可以用三個空間座標 $x^{i}$ 作為 t 的函數來描述。但描述世界線更具四維特色的方式，是將粒子的全部四個座標 $x^{\\alpha}$ 表示為沿世界線變化的參數 $\\sigma$ 的單值函數（見 Figure 5.6）。對於每個 $\\sigma$ 值，四個函數 $x^{\\alpha}(\\sigma)$ 確定曲線上的一點。可選的參數有很多，但一個自然的選擇是固有時，它給出從某個任意起點正負兩方向測量的世界線上的時空距離 $\\tau$。因此，世界線由以下方程描述"
    },
    {
      "i": 84,
      "md": "如我們在 Section 4.3 中所討論的，時鐘是測量類時世界線上距離的裝置。距離 $\\tau$ 可以由沿世界線攜帶的時鐘測量，稱為沿世界線的固有時。"
    },
    {
      "i": 85,
      "caption": "FIGURE 5.6 一條簡單的加速世界線。此時空圖顯示了以固有時 $\\tau$ 為參數，由 (5.24) 參數化描述的世界線。各點標記的 $a\\tau$ 值從 $-1$ 到 $1$，步長為 $\\frac{1}{2}$。各點處以半尺寸繪出了四速度向量 $\\mathbf{u}$。$a\\tau = 1.5$ 與 $-1.5$ 的下一個點超出了圖的範圍。各點在時空幾何中等距，四向量長度相等。你能解釋為什麼在紙面幾何中，各點的間距隨 $|\\tau|$ 增大而看起來增大，向量也看起來隨之變長嗎？"
    },
    {
      "i": 86,
      "md": "Example 5.3. 一條簡單的加速世界線。一個粒子沿 x 軸運動，其世界線由以下參數方程描述"
    },
    {
      "i": 88,
      "md": "其中 $a$ 是具有長度倒數量綱的常數。參數 $\\sigma$ 的範圍為 $-\\infty$ 到 $+\\infty$。對於每個 $\\sigma$ 值，方程 (5.22) 確定時空中的一點 $(t, t)$。（$y$ 和 $z$ 維度對此例不重要，下文將略去。）隨著 $\\sigma$ 的變化，世界線被掃出。Figure 5.6 在時空圖上顯示了這條世界線，它是雙曲線 $x^2 - t^2 = a^{-2}$。因此，世界線也可以用 $x(t) = (t^2 + a^{-2})^{1/2}$ 來描述，但參數化表達式 (5.22) 在 $x$ 與 $t$ 之間更為均衡。世界線是加速的，因為它不是直線。世界線上的固有時 $\\tau$ 與 $\\sigma$ 的關係為 [cf. (4.12), (4.8)]"
    },
    {
      "i": 90,
      "md": "令 $\\sigma$ 為零時 $\\tau$ 也為零，則 $\\tau = a^{-1}\\sigma$，世界線可以以固有時為參數，以 (5.21) 的形式表示為"
    },
    {
      "i": 92,
      "md": "四速度是分量 $u^{\\alpha}$ 為位置沿世界線對固有時參數 $\\tau$ 的導數的四向量 u："
    },
    {
      "i": 93,
      "md": "四速度"
    },
    {
      "i": 95,
      "md": "因此，四速度 $\\mathbf{u}$ 在每點切於世界線，因為位移可寫為 $\\Delta x^{\\alpha} = u^{\\alpha}\\Delta \\tau$。（見 Figure 5.7。）"
    },
    {
      "i": 96,
      "md": "四速度的四個分量可以利用 t 與固有時 $\\tau$ 之間的關係 (4.15)，用特定慣性系中的三速度 $\\vec{V} = d\\vec{x}/dt$ 表示如下："
    },
    {
      "i": 98,
      "md": "以及，例如，"
    },
    {
      "i": 100,
      "md": "總結一下，回憶 (4.22) 中的縮寫 $\\gamma \\equiv (1 - \\vec{V}^2)^{-1 / 2}$，"
    },
    {
      "i": 101,
      "md": "用三速度表示的四速度"
    },
    {
      "i": 103,
      "caption": "FIGURE 5.7 粒子世界線上任意一點的四速度 $\\mathbf{u}(\\tau)$ 是該點的單位類時切四向量，位於該點的光錐內部。這是一幅二維圖，但慣例上會繪製三維光錐，儘管此處只有二維資訊。"
    },
    {
      "i": 104,
      "md": "此結果的一個直接推論是 $\\mathbf{u}$ 與自身的純量積為 [cf. (5.17)]"
    },
    {
      "i": 106,
      "md": "因此四速度始終是單位類時四向量。事實上，若使用 (5.13) 將純量積寫成以下形式，這一點可直接得出"
    },
    {
      "i": 108,
      "md": "其中最後一個等號來自 (5.16) 形式的線元以及關係 $ds^{2} = -d\\tau^{2}$。"
    },
    {
      "i": 109,
      "md": "Example 5.4. 簡單世界線的四速度。Example 5.3 中討論的世界線的四速度 u 的分量為 [cf. (5.25)]"
    },
    {
      "i": 111,
      "md": "其歸一化正確："
    },
    {
      "i": 113,
      "md": "Figure 5.6 中展示了幾個例子。"
    },
    {
      "i": 114,
      "md": "粒子的三速度為"
    },
    {
      "i": 116,
      "md": "這始終不超過光速（$|V^{x}| = 1$），但在 $\\tau = \\pm\\infty$ 時趨近光速。"
    },
    {
      "i": 117,
      "title": "狹義相對論動力學"
    },
    {
      "i": 118,
      "md": "運動方程"
    },
    {
      "i": 119,
      "md": "Newton 第一運動定律在狹義相對論力學和非相對論力學中同樣成立。在無外力的情況下，物體靜止或以恆定速度沿直線運動。這可以概括為"
    },
    {
      "i": 121,
      "md": "四速度的歸一化"
    },
    {
      "i": 122,
      "md": "因為，鑑於 (5.28)，此方程意味著在任意慣性系中 $\\vec{V}$ 為常數。"
    },
    {
      "i": 123,
      "md": "相對論力學的目標是引入 Newton 第二定律 $\\vec{F} = m\\vec{a}$ 的類比。這條定律沒有可以從中推導出來的基礎，但合理地說，它必須滿足某些性質：(1) 它必須滿足"
    },
    {
      "i": 124,
      "md": "Newton 第一定律"
    },
    {
      "i": 125,
      "md": "相對性原理，即在每個慣性系中取相同的形式；(2) 當力為零時，它必須退化為 (5.34)；(3) 在任意慣性系中，當粒子速度遠小於光速時，它必須退化為 $\\vec{F} = m\\vec{a}$。選擇"
    },
    {
      "i": 126,
      "md": "Newton 第二定律"
    },
    {
      "i": 128,
      "md": "靜質量"
    },
    {
      "i": 129,
      "md": "自然浮現出來。常數 $m$ 刻劃粒子的慣性性質，稱為靜質量，而 $\\mathbf{f}$ 稱為四力。要求 (1) 得到滿足，因為這是一個四向量方程；(2) 是顯然的；(3) 在 $\\mathbf{f}$ 的適當選取下得到滿足。這是狹義相對論力學的正確運動定律，也是 Newton 第二定律的狹義相對論推廣。引入四加速度四向量 $\\mathbf{a}$，"
    },
    {
      "i": 130,
      "md": "四加速度"
    },
    {
      "i": 132,
      "md": "運動方程 (5.35) 可以寫成令人印象深刻的形式"
    },
    {
      "i": 134,
      "md": "雖然 $(5.35)$ 代表四個方程，但它們並非全部獨立。四速度的歸一化條件 $(5.29)$ 意味著"
    },
    {
      "i": 136,
      "md": "由 (5.35) 可得 $\\mathbf{u} \\cdot \\mathbf{a} = 0$，即"
    },
    {
      "i": 138,
      "md": "這個關係表明只有三個獨立的運動方程——與 Newton 力學中的數目相同。這一聯繫稍後將更詳細討論，Newton 第三定律也將一併討論。"
    },
    {
      "i": 139,
      "md": "例題 5.5. 所需四力。在 例題 5.3 和 例題 5.4 中描述的世界線上，四加速度 a 的分量為"
    },
    {
      "i": 141,
      "md": "此加速度的大小為 $(\\mathbf{a} \\cdot \\mathbf{a})^{1/2} = a$，因此常數 $a$ 命名恰當。使粒子沿此世界線加速所需的四力為 $\\mathbf{f} = m\\mathbf{a}$，其中 $m$ 是粒子的靜質量。"
    },
    {
      "i": 142,
      "md": "能量-動量"
    },
    {
      "i": 143,
      "md": "運動方程 (5.35) 自然引出能量與動量的相對論概念。若四動量定義為"
    },
    {
      "i": 145,
      "md": "四動量"
    },
    {
      "i": 146,
      "md": "則運動方程 (5.35) 可寫為"
    },
    {
      "i": 148,
      "md": "四動量的一個重要性質由其定義 (5.41) 與四速度的歸一化條件 (5.29) 推得"
    },
    {
      "i": 150,
      "md": "由 (5.28)，四動量的分量與慣性系中的三速度 $\\vec{V}$ 之關係為"
    },
    {
      "i": 152,
      "md": "對於小速度 $V \\ll 1$，"
    },
    {
      "i": 154,
      "md": "因此，在小速度下 $\\vec{p}$ 退化為通常的動量，而 $p^{t}$ 退化為動能加靜質量。因此 p 也稱為能量-動量四向量，其在慣性系中的分量寫為"
    },
    {
      "i": 156,
      "md": "其中 $E \\equiv p^t$ 是能量，$\\vec{p}$ 是三動量。方程 (5.43) 可以對能量求解，以三動量表示為"
    },
    {
      "i": 158,
      "md": "這表明靜能是相對論粒子能量的一部分。事實上，對於靜止粒子，(5.47) 在更常用的單位下退化為 $E = mc^{2}$。這必定是相對論中最著名的方程，甚至是整個物理學中最著名的方程之一。"
    },
    {
      "i": 159,
      "md": "狹義相對論運動學的一個重要應用出現在粒子反應中：在粒子碰撞中總四動量守恆，對應於能量守恆定律和總三動量守恆。一個對天文物理學重要的例子見 Box 5.1（第 94 頁）。"
    },
    {
      "i": 160,
      "md": "在特定慣性系中，相對論運動方程 (5.35) 與 Newton 定律之間的聯繫可以更明確地透過定義三力 $\\vec{F}$ 來建立"
    },
    {
      "i": 162,
      "md": "Newton 第三定律"
    },
    {
      "i": 163,
      "md": "這與 Newton 定律具有相同的形式，但採用三動量的相對論表達式 (5.44)。因此，求解狹義相對論力學問題，本質上與求解 Newton 運動方程相同，唯一的差異在於動量與速度的關係不同 (5.44)。Newton 第三定律對三力 $\\vec{F}$ 同樣適用，就如在 Newton 力學中一樣，因為透過 (5.48)，它意味著粒子系統的總三動量在所有慣性系中守恆。顯然 $\\vec{f} = d\\vec{p}/d\\tau = (d\\vec{p}/dt)(dt/d\\tau) = \\gamma\\vec{F}$。利用 (5.39) 和 (5.28)，四力可以用三力表示為"
    },
    {
      "i": 164,
      "md": "以三力表示的四力"
    },
    {
      "i": 166,
      "md": "其中 $\\vec{V}$ 是粒子的三速度。運動方程 (5.42) 的時間分量為"
    },
    {
      "i": 168,
      "md": "這是 Newton 力學中熟悉的關係。運動方程 (5.42) 的這個時間分量是其餘三個分量的推論。因此，用三力表示時，運動方程與通常 Newton 力學中的形式相同，但採用能量和動量的相對論表達式。當速度較小時，(5.25) 表明 Newton 第二定律的狹義相對論版本 (5.48) 退化為熟悉的非相對論形式。Newton 力學是狹義相對論力學的低速近似。"
    },
    {
      "i": 169,
      "md": "例題 5.6. 磁場中的相對論帶電粒子。一個電荷為 q、靜質量為 m 的粒子在均勻磁場 $\\vec{B}$ 中以總能量 E 運動。其圓形軌道的半徑是多少？作用在粒子上的電磁四力的分量是什麼？"
    },
    {
      "i": 170,
      "md": "如我們已提到的，電磁學在狹義相對論中不變，因此磁場中帶電粒子所受的三力為"
    },
    {
      "i": 172,
      "md": "其中 $\\vec{V}$ 是電荷的速度。粒子以恆定速率在半徑為 R 的圓形軌道上運動，遵從熟悉的運動方程 (5.48)。因此，"
    },
    {
      "i": 174,
      "md": "向心加速度 $d\\vec{V}/dt$ 由純粹運動學的通常關係 $V^{2}/R$ 給出。因此，"
    },
    {
      "i": 176,
      "md": "從而，"
    },
    {
      "i": 178,
      "md": "這將半徑與總能量聯繫起來。四力的分量為 $f^{\\prime} = \\gamma \\vec{F} \\cdot \\vec{V} = 0$（磁場不做功）以及一個徑向分量"
    },
    {
      "i": 180,
      "title": "自由粒子運動的變分原理"
    },
    {
      "i": 181,
      "md": "Newton 力學可以由一個極值作用量原理加以概括，如 Section 3.5 所述。狹義相對論中自由粒子的運動同樣可以由一個類似的變分原理加以概括——極值固有時原理。這一原理從 Section 4.4 的雙生子悖論討論中已經顯而易見。自由粒子在時空中運動所走的直線，是兩個事件之間固有時最長的路徑。本節將論證這一事實構成了一個變分原理，並由此導出自由粒子的運動方程 (5.34)。這一點非常重要，因為在 Chapter 8 中，我們將反轉這一論證：對彎曲時空中自由粒子提出極值固有時原理，並用它推導自由粒子的運動方程。"
    },
    {
      "i": 182,
      "md": "極值固有時的變分原理可陳述如下："
    },
    {
      "i": 183,
      "md": "自由粒子運動的變分原理"
    },
    {
      "i": 184,
      "md": "自由粒子在兩個類時分隔點之間的世界線，使它們之間的固有時取極值。"
    },
    {
      "i": 185,
      "md": "考慮時空中兩個類時分隔的點 A 和 B，以及在它們之間通過的所有類時世界線（Figure 5.8）。每條曲線都有一個"
    },
    {
      "i": 186,
      "caption": "FIGURE 5.8 兩點之間的直線，與連接兩點的鄰近曲線（陰影部分）相比，是兩點之間距離的極值。"
    },
    {
      "i": 187,
      "md": "固有時"
    },
    {
      "i": 189,
      "md": "設世界線由參數 $\\sigma$ 参數化，選取 $\\sigma$ 使得對所有我們要考慮的曲線，$\\sigma = 0$ 對應點 A，$\\sigma = 1$ 對應點 B（這對參數 $\\tau$ 而言不成立）。世界線由座標作為 $\\sigma$ 的函數給出，即 $x^{\\alpha} = x^{\\alpha}(\\sigma)$。方程 (5.56) 可寫為"
    },
    {
      "i": 191,
      "md": "我們尋找使 $\\tau_{AB}$ 取極值的世界線，即對小變分 $\\delta x^{\\alpha}(\\sigma)$ 使固有時的變分為零的曲線。這是 Newton 力學中熟悉的一類問題，已在 Section 3.5 中回顧。將 (5.57) 中的被積函數視為 Lagrange 量，$x^{\\alpha}$ 視為動力學變數，$\\sigma$ 視為時間，則 (5.57) 與 Newton 力學的作用量 (3.35) 具有相同形式。Lagrange 方程是在這裡和那裡取極值的必要條件。具體地說，"
    },
    {
      "i": 193,
      "md": "其中"
    },
    {
      "i": 195,
      "md": "為了了解發生了什麼，我們寫出 $x^{1} \\equiv x$ 的 Lagrange 方程 (5.58)："
    },
    {
      "i": 197,
      "md": "然而，$L = [-\\eta_{\\alpha \\beta}(dx^{\\alpha} / d\\sigma)(dx^{\\beta} / d\\sigma)]^{1 / 2}$ 恰好是 $d\\tau /d\\sigma$，因此乘以 $d\\sigma /d\\tau$ 後，(5.60) 變為"
    },
    {
      "i": 199,
      "md": "其他座標的情況完全相同。所有四個 Lagrange 方程均蘊含"
    },
    {
      "i": 201,
      "md": "這正是自由粒子的正確運動方程 (5.34)。其解為連接 A 和 B 的直世界線。平坦時空中自由粒子的世界線是固有時取極值的曲線。"
    },
    {
      "i": 202,
      "title": "光線"
    },
    {
      "i": 203,
      "md": "零靜質量粒子"
    },
    {
      "i": 204,
      "md": "迄今為止的討論涉及靜質量非零、以低於光速運動的粒子。現在讓我們考慮以光速 $V = 1$ 沿零世界線運動的粒子。例子包括光和重力的量子——光子和重力子——以及可能某些種類的微中子。$^{4}$ 我們幾乎完全專注於光子，在其非量子方面也稱為光線，但我們的處理同樣適用於任何以光速運動的其他粒子。"
    },
    {
      "i": 205,
      "md": "顯然，固有時不再能作為光線世界線的參數——光線上任意兩點之間的固有時間隔為零。然而，可以使用許多其他參數。例如，曲線"
    },
    {
      "i": 207,
      "md": "其中 $V = 1$，可以參數化地寫為"
    },
    {
      "i": 209,
      "md": "其中 $\\lambda$ 是參數，$u^{\\alpha} = (1, 1, 0, 0)$。四向量 $\\mathbf{u}$ 是切四向量 $u^{\\alpha} = dx^{\\alpha}/d\\lambda$，以參數 $\\lambda$ 代替 (5.25) 中的 $\\tau$。然而，這裡是一個零向量。因此，與 (5.29) 相比，"
    },
    {
      "i": 211,
      "md": "不同的參數化選取會給出不同的切四向量，但所有切向量的長度均為零。"
    },
    {
      "i": 212,
      "md": "在此參數化選取下，"
    },
    {
      "i": 214,
      "md": "因此光線的運動方程與粒子的運動方程 (5.34) 相同。還有許多其他參數化選取不滿足這一點。例如，可以在 (5.64) 中用 $\\sigma^3$ 替換 $\\lambda$。隨著 $\\sigma$ 在 $-\\infty$ 到 $\\rightarrow x$ 之間變化，同一條直線 $x = t$ 依然被描述。(5.65) 繼續成立，但 (5.66) 不再成立。使光線的運動方程 (5.66) 與粒子具有相同形式的參數稱為仿射參數。仿射參數並不唯一。例如，若 $\\lambda$ 是仿射參數，則常數乘以 $\\lambda$ 也是仿射參數。仿射參數"
    },
    {
      "i": 215,
      "md": "目前有證據表明，至少某些種類的微中子具有小的靜質量。"
    },
    {
      "i": 216,
      "md": "仿射參數"
    },
    {
      "i": 217,
      "md": "是光線最方便使用的參數，因為 (5.66) 具有簡單的形式。"
    },
    {
      "i": 218,
      "md": "能量、動量、頻率與波向量"
    },
    {
      "i": 219,
      "md": "光子和微中子攜帶能量和三動量。在任意慣性系中，光子的能量 E 與其頻率 $\\omega$ 由 Einstein 的另一著名關係相連，"
    },
    {
      "i": 221,
      "md": "對於三動量，注意由 (5.44) 可知三速度為 $\\vec{V} = \\vec{p}/E$。由於 $|\\vec{V}| = 1$，這意味著對光子 $|\\vec{p}| = E$，因此三動量可寫為"
    },
    {
      "i": 223,
      "md": "其中 $\\vec{k}$ 指向傳播方向，大小為 $|\\vec{k}| = \\omega$，稱為波三向量。因此在任意慣性系中，光子四動量 p 的分量可寫為"
    },
    {
      "i": 224,
      "md": "光子的四動量"
    },
    {
      "i": 226,
      "md": "四向量 k 稱為波四向量。顯然，"
    },
    {
      "i": 228,
      "md": "將此與 (5.43) 比較，可見光子的靜質量為零，就如所有以光速運動的粒子一樣。p 和 k 都切於光子的世界線。切向量 u 可以通過調整仿射參數 $\\lambda$ 的歸一化與 p 或 k 重合。運動方程 (5.66) 可以用 p 或 k 寫為"
    },
    {
      "i": 230,
      "md": "其中 $\\lambda$ 是仿射參數。"
    },
    {
      "i": 231,
      "md": "都卜勒頻移與相對論集束效應"
    },
    {
      "i": 232,
      "md": "相對論都卜勒頻移是這些思想的簡單應用。考慮一個在光源靜止系中向所有方向發射頻率為 $\\omega$ 的光子的光源。設在另一個參考系中，光源沿 $x'$ 軸以速度 V 運動。對於與運動方向夾角為 $\\alpha'$ 的光子，觀察者會測得什麼頻率？這個問題通過使用 Lorentz 推進，將靜止系中波四向量 k 的分量與光源運動的觀察者系中的分量相聯繫來回答。設 $k^{\\alpha} = (\\omega, \\vec{k})$ 為光子波四向量 k 在光源系中的分量，$k'^{\\alpha} = (\\omega', \\vec{k}')$ 為在觀察者系中的分量。由 (5.9)，"
    },
    {
      "i": 234,
      "md": "但 $k'^{x} = \\omega' \\cos \\alpha'$，其中 $\\alpha'$ 是 $x'$ 軸與光子在觀察者系中方向之間的夾角。因此，"
    },
    {
      "i": 236,
      "md": "都卜勒頻移"
    },
    {
      "i": 237,
      "md": "這是相對論都卜勒頻移的公式。對小速度 V，這近似為"
    },
    {
      "i": 239,
      "md": "當 $\\alpha' = 0$ 時，光子在光源運動的相同方向上發射，光子頻率有藍移 $\\Delta\\omega' = +V\\omega$。當 $\\alpha = \\pi$ 時，光子運動方向與光源相反，有紅移 $\\Delta\\omega' = -V\\omega$。"
    },
    {
      "i": 240,
      "md": "即使是橫向於光源運動方向發射的光子（$\\alpha' = \\pi 2$）也有紅移，儘管此效應的首項為 $V^{2}$ 量級。這稱為橫向都卜勒頻移，公式 (5.73) 表明它正是時間膨脹。"
    },
    {
      "i": 241,
      "md": "相對論集束效應（Figure 5.9）源於光子空間動量的變換。設光子在光源系中與 $x$ 軸夾角為 $\\alpha$，其中 $\\cos \\alpha = k^x / \\omega$。在觀察者系中，它與 $x'$ 軸的夾角定義為 $\\cos \\alpha' = k'^x / \\omega'$。連接 $(\\omega, k^x)$ 與 $(\\omega', k'^x)$ 的兩系之間的 Lorentz 變換 (5.9) 表明這兩個角度的關係為"
    },
    {
      "i": 243,
      "md": "相對論集束效應"
    },
    {
      "i": 244,
      "md": "因此，在源框架中向前半球發射的光子（$\\alpha_{1}<\\pi/2$），被觀察者看到是在較小錐體 $|\\alpha^{\\prime}|<\\alpha_{1/2}^{\\prime}$ 內發射，其中 $\\cos\\alpha_{1/2}^{\\prime}=V$。當 $V$ 接近 1 時，此張角將會很小。因此光子因源的運動而沿源的方向集束。Doppler 頻移意味著前向光子的能量大於後向光子，這表示輻射強度沿運動方向更加集中（Problem 17）。一個均勻輻射的物體朝向你運動時比遠離你時更亮。這就是相對論性集束（relativistic beaming）現象。"
    },
    {
      "i": 245,
      "caption": "FIGURE 5.9 相對論性集束。左圖顯示一個在其靜止系中向所有方向均勻輻射的物體，圖中畫出了垂直於表面發射的 24 個光子的波向量。右圖顯示在 Lorentz 收縮後的物體在以速度 $V = .75$ 向右運動的參考系中，以及同樣 24 個光子的波向量。隨著 $V$ 趨近光速，光子越來越沿運動方向集中，且由於 Doppler 效應，其波向量在該方向的分量也越來越大。因此輻射強度沿運動方向越來越集中。"
    },
    {
      "i": 246,
      "md": "BOX 5.1 宇宙微波背景對宇宙射線能量的截斷"
    },
    {
      "i": 247,
      "md": "宇宙中相對地球以低於光速運動的最快粒子，是能量最高的宇宙射線。宇宙射線是在星際介質中傳播的基本粒子或原子核的統稱。質子是常見的例子。宇宙射線通過它們進入大氣層時產生的粒子簇射被探測到，已觀測到的能量高達 $3 \\times 10^{20}$ eV。與大氣中質子的碰撞比地球上最強大加速器中的碰撞高 100,000 倍。對於質子而言，這對應 $\\gamma \\sim 10^{11}$，速度僅比光速低 $10^{22}$ 分之幾。"
    },
    {
      "i": 248,
      "md": "宇宙射線的加速機制尚不完全清楚，但通過研究它們與宇宙微波背景輻射（CMB）光子的相互作用，可以找到關於其起源的一些線索。CMB 是一種瀰漫全宇宙的、來自大霹靂的黑體背景光，目前已冷卻至 2.73 K。我們在 Chapter 17 中詳細研究 CMB，但要考慮其對宇宙射線的影響，只需幾個基本事實。在稱為 CMB 框架的參考系中，輻射是具有黑體譜的各向同性輻射。星系相對於此框架的運動速度遠小於光速。在 2.73 K 溫度下，CMB 光子的特徵能量為 $2 \\times 10^{-4}$ eV，平均每 cm$^3$ 中有 400 個 CMB 光子。"
    },
    {
      "i": 249,
      "md": "當高能宇宙射線質子與 CMB 光子碰撞時會發生什麼？如果質子的速度足夠快，碰撞可以引發如光生介子（pion photoproduction）等反應，"
    },
    {
      "i": 251,
      "md": "這些反應將使質子的能量降低。（儘管可能造成混淆，我們仍然同時使用 $\\gamma$ 表示光子和 Lorentz 變換中的因子。）如果宇宙射線質子的源足夠遙遠，以至於它們幾乎必然在到達我們的途中與某個 CMB 光子發生碰撞，那麼我們就不應期望看到能量超過此值的宇宙射線質子。這個限制被稱為 GZK 截斷，以首先提出此效應的作者姓名首字母命名（Greisen-Zatsepin-Kuz'min）。"
    },
    {
      "i": 252,
      "md": "計算 GZK 截斷能量是一個關於狹義相對論的有益練習。為明確起見，考慮前述第一個過程。總四動量守恆："
    },
    {
      "i": 254,
      "md": "閾值能量在質心（CM）系中最容易求得，在該系中兩碰撞粒子的動量大小相等、方向相反。閾值發生在初始能量恰好足以使中子和介子都靜止的情況。"
    },
    {
      "i": 255,
      "md": "在 CM 系的閾值處，總能量為 $E_{n}^{CM} + E_{\\pi}^{CM} = m_{n} + m_{\\pi}$。總三動量按定義為零，$\\vec{p}_{n}^{CM} + \\vec{p}_{\\pi}^{CM} = 0$。這在 CMB 框架中對應怎樣的能量 $E_{p}^{CMB}$？在該框架中光子具有典型能量 $E_{\\gamma}^{CMB} \\approx 6 \\times 10^{-4}$ eV？那個閾值質子能量就是 GZK 截斷。"
    },
    {
      "i": 256,
      "md": "這個問題可以利用四向量長度在所有框架中相同這一事實來有效地回答。在 CM 系中的閾值處計算 $(\\mathbf{p}_{n} + \\mathbf{p}_{\\pi})^{2}$，得到 $-(m_{n} + m_{\\pi})^{2}$。四動量守恆（a）意味著這與 $(\\mathbf{p}_{\\gamma} + \\mathbf{p}_{p})^{2}$ 相同。利用 $p_{p}^{2} = -m_{p}^{2}$ 和 $p_{\\gamma}^{2} = 0$（光子靜質量為零）計算該平方，得到"
    },
    {
      "i": 258,
      "md": "這個關係不依賴於框架，但可以用 CMB 框架中四動量的分量來計算。設質子能量為 $E_{p}^{CMB} \\gg m_{p}$，沿 $x$ 軸運動，與能量為 $E_{\\gamma}^{CMB}$ 的光子對撞，光子沿相反方向運動。CMB 框架 $(t, x)$ 分量為"
    },
    {
      "i": 261,
      "md": "其中三動量已利用 (5.47) 用能量表示，並採用近似 $E_{p}^{CMB} \\gg m_{p}$。(b) 中的純量積可以用這些分量計算，所得關係可求解 $E_{p}^{CMB}$。利用近似 $m_{n} \\approx m_{p}$（對目前目的而言已足夠精確），結果化簡為"
    },
    {
      "i": 263,
      "md": "這就是 GZK 截斷能量。這些質子的速度 $V$ 僅比光速低 $5 \\times 10^{-24}$，對應的 Lorentz $\\gamma$ 因子 $\\gamma \\sim 10^{11}$！"
    },
    {
      "i": 264,
      "md": "$10^{20}$ eV 質子在與 CMB 光子碰撞前的平均自由程 $\\lambda_{CMB} = 1 / (\\sigma N_{\\gamma})$，其中 $\\sigma$ 為光生介子過程的截面——約 $2 \\times 10^{-28}\\mathrm{cm}^2$——$N_{\\gamma}$ 為 CMB 光子數密度——約 $400~\\mathrm{cm}^{-3}$。這些數字給出 $\\lambda_{CMB} \\approx 10^{25}\\mathrm{cm} \\approx 10$ 百萬光年。這僅比本星系群的尺度大幾倍。質子能量衰減只需幾個平均自由程，但具有那種能量的質子不可能來自太遠的地方。非常高能量的宇宙射線很稀少，但已在 $3 \\times 10^{20}\\mathrm{eV}$ 能量處被探測到，而且沒有跡象顯示數量急劇減少——這正是 GZK 截斷所預期的。對高能粒子的一種解釋是它們產生於附近。"
    },
    {
      "i": 265,
      "title": "觀察者與觀測"
    },
    {
      "i": 266,
      "md": "狹義相對論力學的預測通常在慣性系中最容易計算和理解。靜止在慣性系中的觀察者的觀測結果參照該框架的座標軸。例如，靜止在慣性系中的觀察者所測量的粒子能量，是粒子四動量沿該框架時間軸的分量。但並非每個觀察者都靜止在慣性系中——例如，地球表面的觀察者就不是。如何計算加速觀察者的觀測預測？"
    },
    {
      "i": 267,
      "caption": "FIGURE 5.10 在時空中運動的觀察者可以想像為攜帶一個局部實驗室，如左圖所示，沿世界線在時空中運動。如右圖所示，實驗室內三個相互正交的空間方向定義了三個類空單位四向量 $\\mathbf{e}_{\\hat{1}}$、$\\mathbf{e}_{\\hat{2}}$、$\\mathbf{e}_{\\hat{3}}$。觀察者靜止於實驗室中的時鐘定義了時間方向 $\\mathbf{e}_{\\hat{0}}$，與觀察者的四速度一致。觀察者所做的觀測都參照基四向量 $\\mathbf{e}_{\\hat{\\alpha}}$，$\\hat{\\alpha} = 0, 1, 2, 3$。"
    },
    {
      "i": 268,
      "md": "這個問題對廣義相對論尤為重要。在廣義相對論的彎曲時空中，通常不存在延伸到整個時空的慣性系。如我們將看到的，在每個點的鄰域以及自由下落觀察者世界線的鄰域內存在局部慣性系，但不存在整體慣性系。因此，建立一種系統的方法來提取與整體慣性系無關的觀察者的預測至關重要。本節描述如何在狹義相對論的背景下做到這一點。"
    },
    {
      "i": 269,
      "md": "觀察者在時空中的路徑是一條類時世界線。觀察者可以想像為沿世界線攜帶一個實驗室。至少對天體物理問題而言，即使是哈伯太空望遠鏡這樣的實驗室，相對於物理現象發生的距離而言也非常小。因此，我們將其理想化為任意小的。在實驗室內，觀察者通過時鐘和尺進行測量。（見 Figure 3.1。）例如，觀察者可以通過注意粒子路徑與實驗室某面牆的夾角（給出方向），以及測量粒子穿越實驗室距離所需的時間（給出速率），來測量穿過實驗室的粒子速度。"
    },
    {
      "i": 270,
      "md": "從數學上看，局部實驗室的概念可以如 Figure 5.10 所示來理想化。觀察者攜帶四個相互正交的單位四向量 $\\mathbf{e}_0$、$\\mathbf{e}_1$、$\\mathbf{e}_2$、$\\mathbf{e}_3$，分別定義時間方向和三個空間方向，觀察者將所有測量量都參照這些方向。帶帽指標用來強調我們處理的是正交歸一基底——每個四向量長度為 1，且所有四向量互相正交。類時單位四向量 $e_{\\hat{0}}$ 與觀察者世界線相切，因為這是實驗室中靜止時鐘在時空中的運動方向。由於觀察者的四速度 $u_{obs}$ 是單位切向量 [參見 (5.29)]，"
    },
    {
      "i": 272,
      "md": "觀察者可以自由選擇三個空間基向量 $e_{\\hat{i}}$，只要它們與 $e_{\\hat{0}}$ 正交且彼此正交即可。只有當實驗室靜止在慣性系中時，$e_{\\hat{\\alpha}}$ 才會指向慣性系的座標軸方向。"
    },
    {
      "i": 273,
      "md": "例題 5.7. 一個簡單加速觀察者的正交歸一基底。考慮沿 Examples 5.3 和 5.4 中描述的加速世界線運動的觀察者。在慣性系中，該觀察者的一組正交歸一基四向量的分量是什麼？這些四向量將隨觀察者的固有時變化。四向量 $\\mathbf{e}_{\\hat{0}}(\\tau)$ 是觀察者的四速度 $\\mathbf{u}_{\\mathrm{obs}}(\\tau)$，其分量為 [參見 (5.31)]"
    },
    {
      "i": 275,
      "md": "其他三個四向量 $\\mathbf{e}_{\\hat{i}}(\\tau)$ 的唯一條件是它們與 $\\mathbf{e}_{\\hat{0}}(\\tau)$ 正交、彼此正交，且長度為 1。對應於觀察者選擇正交歸一系空間軸方向的自由，存在許多可能的選擇。滿足這些條件最簡便的方法是分別選取 $\\mathbf{e}_{\\hat{2}}(\\tau)$ 和 $\\mathbf{e}_{\\hat{3}}(\\tau)$ 為 $y$ 和 $z$ 方向的單位四向量。剩餘四向量 $\\mathbf{e}_{\\hat{1}}(\\tau)$ 則具有 $(f(\\tau), g(\\tau), 0, 0)$ 的形式，其中 $f$ 和 $g$ 為某些函數。與 $\\mathbf{e}_{\\hat{0}}(\\tau)$ 正交意味著"
    },
    {
      "i": 277,
      "md": "單位長度意味著"
    },
    {
      "i": 279,
      "md": "這兩個條件確定了 $f$ 和 $g$。與 (5.77) 一起構成觀察者正交歸一基四向量的 $\\mathbf{e}_i(\\tau)$ 為"
    },
    {
      "i": 283,
      "md": "如前所述，觀察者將觀測量參照其實驗室座標軸和其中的時鐘。這意味著他們測量四向量沿基四向量 $\\{\\mathbf{e}_{\\hat{\\alpha}}\\}$ 的分量（符號 $\\{\\}$ 表示「集合」）。例如，加速觀察者測量到的粒子能量，是粒子四動量 $\\mathbf{p}$ 沿基四向量 $\\mathbf{e}_{\\hat{0}}$ 的分量。沿 1 方向測量的三動量是 $\\mathbf{p}$ 沿 $\\mathbf{e}_{\\hat{1}}$ 的分量，以此類推。這些分量由以下分解定義 [參見 (5.4)]"
    },
    {
      "i": 285,
      "md": "它們可以計算為與觀察者正交歸一基四向量的純量積，暫時放寬指標平衡規則$^{5}$，可以寫作"
    },
    {
      "i": 287,
      "md": "要驗證這些關係，只需利用 (5.81) 計算右端各項，並考慮到基四向量是正交歸一的。特別地，觀察者測量到的粒子能量 $E$，即其中第一個，或"
    },
    {
      "i": 289,
      "md": "以下例題說明這是如何運作的。"
    },
    {
      "i": 290,
      "caption": "FIGURE 5.11 一個運動經過靜止粒子的觀察者，將粒子能量測量為四動量沿觀察者四速度方向的分量。"
    },
    {
      "i": 291,
      "md": "觀察者測量的能量"
    },
    {
      "i": 292,
      "md": "例題 5.8. 以速度 $V$ 運動的觀察者測量靜止粒子的能量。考慮一個在某慣性系中靜止的粒子（Figure 5.11）。一個觀察者以速度 $\\vec{V}$ 在該系中運動，使得觀察者的世界線與粒子的世界線相交。從觀察者的角度看，粒子穿過觀察者的實驗室。觀察者將測量到粒子的什麼能量？我們已經知道答案。粒子將以速度 $V$ 穿過實驗室，因此測得的能量將是"
    },
    {
      "i": 294,
      "md": "其中 $m$ 是粒子的靜質量。"
    },
    {
      "i": 295,
      "md": "讓我們通過與觀察者正交歸一基的純量積來說明這是如何得出的。在粒子靜止的慣性系中，粒子的動量四向量分量為"
    },
    {
      "i": 297,
      "md": "在同一框架中，觀察者的四速度為 [參見 (5.28)]"
    },
    {
      "i": 299,
      "md": "根據 $(5.82)$，觀察者測量到的能量為"
    },
    {
      "i": 301,
      "md": "這與 (5.84) 相同。觀察者測量到的能量正是粒子能量-動量四向量沿觀察者時間方向 $\\mathbf{e}_{\\hat{0}}$ 的分量。"
    },
    {
      "i": 302,
      "md": "對這個簡單例題而言，計算 (5.87) 過於繁瑣。然而重點在於，表達式 (5.87) 是以不變形式寫出的，可以在任何參考系中計算。為了看出這樣做的優勢，請考慮以下例題。"
    },
    {
      "i": 303,
      "md": "例題 5.9. 加速觀察者測量的頻率。一個沿 Examples 5.3 和 5.4 世界線運動的觀察者，觀測一顆靜止在慣性系原點的恆星發出的光，假設恆星持續發光。為簡單起見，假設光在恆星靜止系中以單一光頻 $\\omega_{*}$ 發出。觀察者沿其世界線將測量到什麼頻率 $\\omega(\\tau)$（作為固有時的函數）？"
    },
    {
      "i": 304,
      "md": "在恆星靜止的慣性系中，到達觀察者的光子的波四向量 $k$ 具有分量 $k^{\\alpha} = (\\omega_{*}, \\omega_{*}, 0, 0)$。觀測頻率 $\\omega(\\tau)$ 可以通過將這些分量變換到固有時 $\\tau$ 時觀察者的瞬時靜止系來求得。這並不太困難（Problem 18），但更便捷的方法是注意對光子有 $E = \\hbar\\omega$，並使用 (5.87)："
    },
    {
      "i": 306,
      "md": "其中 $\\mathbf{u}_{\\mathrm{obs}}$ 為四速度 (5.31)。明確地，這給出"
    },
    {
      "i": 308,
      "md": "在固有時較早時，觀察者快速向源靠近，光發生藍移；在固有時較晚時，觀察者快速遠離源，光發生紅移。"
    },
    {
      "i": 309,
      "md": "一個在艦橋上沿世界線 (5.31) 行進並觀看星空的觀察者，只能在固有時量級為 $1/a$ 的有限時間內看到這些恆星。你能解釋為什麼嗎？"
    }
  ],
  "problems": [
    {
      "num": "1",
      "body": [
        {
          "i": 0,
          "md": "[S] 考慮兩個四向量 $\\mathbf{a}$ 和 $\\mathbf{b}$，其分量為"
        },
        {
          "i": 3,
          "md": "(a) $\\mathbf{a}$ 是類時、類空還是類光？$\\mathbf{b}$ 是類時、類空還是類光？\n\n(b) 計算 $\\mathbf{a} - 5\\mathbf{b}$。\n\n(c) 計算 $\\mathbf{a} \\cdot \\mathbf{b}$。"
        }
      ]
    },
    {
      "num": "10",
      "body": [
        {
          "i": 0,
          "md": "在 CERN 的 LEP 粒子加速器中，電子和正電子在一個半徑約 10 km 的圓環中以相反方向運動，各自能量為 100 GeV。"
        },
        {
          "i": 1,
          "md": "(a) 這些粒子的速度與光速相差多少？\n\n(b) 電子和正電子可以儲存 2 小時。在此時間內，電子或正電子繞環多少圈？"
        }
      ]
    },
    {
      "num": "11",
      "body": [
        {
          "i": 0,
          "md": "以 (4.18) 中用於描述 Lorentz 推進的參數 $\\theta$ 來表示平行速度相加定律。你能給出這一結果的幾何詮釋嗎？"
        }
      ]
    },
    {
      "num": "12",
      "body": [
        {
          "i": 0,
          "md": "2 英里長的史丹佛直線加速器在加速器靜止系中將電子加速到 40 GeV 的能量。將加速機制理想化為沿加速器的均勻電場 $\\vec{E}$，假設運動方程為"
        },
        {
          "i": 2,
          "md": "其中 $\\vec{p}$ 是相對論動量 $\\mathbf{p}$ 的空間部分。"
        },
        {
          "i": 3,
          "md": "(a) 假設電子從靜止開始，以靜質量 $m$ 和 $F \\equiv e|\\vec{E}|$ 表示電子沿加速器的位置作為時間的函數。\n\n(b) 要將粒子加速到最終能量，需要多大的 $|\\vec{E}|$？"
        }
      ]
    },
    {
      "num": "13",
      "body": [
        {
          "i": 0,
          "md": "[B, S] 光生介子的一個反應為"
        },
        {
          "i": 2,
          "md": "求在質子靜止系中，光子產生介子所需的最低能量（閾值能量）。這一能量是否在當代加速器的範圍之內？"
        }
      ]
    },
    {
      "num": "14",
      "body": [
        {
          "i": 0,
          "md": "[B] 比較能量最高的宇宙射線與你用力投出的石頭的能量。"
        }
      ]
    },
    {
      "num": "15",
      "body": [
        {
          "i": 0,
          "md": "[C] 一個源和一個探測器在旋轉圓盤邊緣上相隔某角度 $\\phi$。源在其瞬時靜止系中以頻率 $\\omega_{*}$ 發射輻射。探測器接收到的頻率是多少？提示：本題給出的資訊很少，因為所需的也很少。"
        }
      ]
    },
    {
      "num": "16",
      "body": [
        {
          "i": 0,
          "md": "光行差 考慮一顆恰好在午夜位於天頂正上方、且處於地球軌道平面內的恆星。為了通過望遠鏡觀測該恆星，望遠鏡軸必須相對於天頂方向沿地球在軌道中運動的方向傾斜一個小角度。解釋原因並計算該角度。為簡化情況，可以假設地球軌道近似為圓形，且如有必要，可假設自轉軸垂直於軌道平面。"
        }
      ]
    },
    {
      "num": "17",
      "body": [
        {
          "i": 0,
          "md": "[C] 相對論性集束 一個物體在其靜止系中向所有方向以相同速率發射頻率為 $\\omega_{*}$ 的光子。在該系中距物體很遠（遠大於物體尺寸）靜止的探測器，每單位立體角接收光子的速率 $(dN / dtd\\Omega)_{*}[\\text{個光子}/(\\text{s} \\cdot \\text{sr})]$ 與方向無關。在一個慣性系 $(t', x', y', z')$ 中，一個靜止的觀察者看到物體以速度 $V$ 沿 $x'$ 軸運動。"
        },
        {
          "i": 1,
          "md": "(a) 推導 (5.75)，即靜止系中光子傳播方向與觀察者系中傳播方向之間的關係。"
        },
        {
          "i": 2,
          "md": "(b) 求在觀察者系中，在距離很遠處每單位立體角接收光子的速率 $dN / dt' d\\Omega'$，作為與 $x'$ 軸夾角 $\\alpha'$ 的函數。\n\n(c) 求在觀察者系中，在距離很遠處每單位立體角的光度 $dL' / d\\Omega'[\\mathrm{erg} / (\\mathrm{s}\\cdot \\mathrm{sr})]$，作為觀察者系中角度 $\\alpha'$ 的函數。\n\n(d) 當源的速度趨近光速時，討論在觀察者系中光子數目和能量的集束效應。"
        },
        {
          "i": 3,
          "md": "18. 通過將光子波向量的分量變換到固有時 $\\tau$ 時觀察者的瞬時靜止系，求出 Example 5.9 中觀察者所見頻率作為固有時的函數。\n\n19. [S] 一個觀察者以恆定速度 $V$ 沿慣性系的 $x$ 軸運動。求在該系中正交歸一基四向量 $\\{e_{\\hat{\\alpha}}\\}$ 的分量，觀察者可以用這些基向量來參照觀測結果。\n\n20. 考慮一個四動量為 $\\mathbf{p}$ 的粒子和一個四速度為 $\\mathbf{u}$ 的觀察者。證明若粒子穿過觀察者的實驗室，則測量到的三動量大小為"
        }
      ]
    },
    {
      "num": "2",
      "body": [
        {
          "i": 0,
          "md": "兩個三向量的純量積可以寫為"
        },
        {
          "i": 2,
          "md": "其中 $a$ 和 $b$ 分別是 $\\vec{a}$ 和 $\\vec{b}$ 的長度，$\\theta_{ab}$ 是它們之間的夾角。證明對兩個類時四向量 $\\mathbf{a}$ 和 $\\mathbf{b}$ 有類比公式成立。"
        },
        {
          "i": 4,
          "md": "其中 $a = (-\\mathbf{a} \\cdot \\mathbf{a})^{1/2}$，$b = (-\\mathbf{b} \\cdot \\mathbf{b})^{1/2}$，$\\theta_{ab}$ 是 (4.18) 中定義的參數，描述世界線沿 $\\mathbf{a}$ 方向的觀察者靜止系與世界線沿 $\\mathbf{b}$ 方向的觀察者靜止系之間的 Lorentz 推進。"
        },
        {
          "i": 5,
          "md": "3. [S] 一個自由粒子沿慣性系的 $x$ 軸運動，速度（三速度的大小）為 $dx/dt = V$，在 $t = 0$ 時經過原點。用固有時 $\\tau$ 作為參數，以 $V$ 參數化粒子的世界線。\n\n4. 以三速度 $\\vec{V}$ 和三加速度 $\\vec{a} = d\\vec{V}/dt$ 寫出四加速度向量 $a \\equiv d\\mathbf{u}/d\\tau$ 的分量，得到類似於 (5.28) 的表達式。利用此表達式和 (5.28)，明確驗證 $a \\cdot u = 0$。\n\n5. 複製 Figure 5.6，並以半比例在圖上畫出各點的加速度四向量 $\\mathbf{a}$。這些向量與 $\\mathbf{u}$ 正交嗎？\n\n6. 考慮一個沿 $x$ 軸運動的粒子，其速度作為時間的函數為"
        },
        {
          "i": 7,
          "md": "其中 $g$ 是常數。"
        },
        {
          "i": 8,
          "md": "(a) 粒子速度是否曾超過光速？\n\n(b) 計算粒子四速度的分量。\n\n(c) 將 $x$ 和 $t$ 表示為軌跡固有時的函數。\n\n(d) 作用在粒子上的四力和三力的分量是什麼？"
        }
      ]
    },
    {
      "num": "21",
      "body": [
        {
          "i": 0,
          "md": "[P, A] 假設在所有慣性系中，帶電粒子所受的力由通常的 Lorentz 力定律給出："
        },
        {
          "i": 2,
          "md": "其中 $q$ 是粒子的電荷，$\\vec{V} \\equiv d\\vec{x}/dt$ 是其三速度，$\\vec{E}$ 和 $\\vec{B}$ 是在 Lorentz 系中測量的電場和磁場。考慮另一個相對第一個慣性系以速度 $v$ 沿 $x$ 軸運動的慣性系。"
        },
        {
          "i": 3,
          "md": "(a) 以 $\\vec{E}$、$\\vec{B}$ 和粒子四速度 $\\mathbf{u}$ 的分量，求四力 $\\mathbf{f}$ 的分量。\n\n(b) 利用 $\\mathbf{f}$ 和 $\\mathbf{u}$ 分量的變換法則，對原慣性系中下列特殊場求出新慣性系中的電場和磁場變換規則："
        },
        {
          "i": 4,
          "md": "(i) $x$ 方向的電場。\n\n(ii) $x$ 方向的磁場。\n\n(iii) $y$ 方向的電場。\n\n(iv) $y$ 方向的磁場。"
        }
      ]
    },
    {
      "num": "22",
      "body": [
        {
          "i": 0,
          "md": "[C] 相對論火箭 火箭通過以尾氣形式噴出部分靜質量來加速。尾氣在火箭靜止系中的速率為恆定值 $u$。利用能量和動量守恆，求從靜止加速到速度 $V$ 的火箭，最終靜質量與初始靜質量之比。提示：靜質量不守恆——守恆的是能量和動量。你可以先從 Newton 力學中的同一問題入手。"
        }
      ]
    },
    {
      "num": "23",
      "body": [
        {
          "i": 0,
          "md": "[C] 快子（Tachyons）"
        },
        {
          "i": 1,
          "md": "(a) 論證一種始終以超過光速的速度運動的粒子在 Lorentz 不變性的意義下是自洽的，即若其速度在某一框架中超過光速，則在所有框架中都超過光速。（此類假想粒子稱為快子（tachyons）。）"
        },
        {
          "i": 2,
          "md": "(b) 證明快子軌跡的切向量是類空的，可以寫作 $u^{\\alpha} = dx^{\\alpha} / ds$，其中 $s$ 是沿軌跡的類空間隔。證明 $\\mathbf{u} \\cdot \\mathbf{u} = 1$。\n\n(c) 以三速度 $\\vec{V} = d\\vec{x}/dt$ 計算快子四速度 $\\mathbf{u}$ 的分量。\n\n(d) 以 $\\mathbf{p} = m\\mathbf{u}$ 定義四動量，求快子能量與動量之間的關係。\n\n(e) 證明存在一個慣性系使任意快子的能量為負。\n\n(f) 證明若快子與普通粒子相互作用，普通粒子可以在總能量和三動量守恆的條件下發射一個快子。"
        },
        {
          "i": 3,
          "md": "注：(f) 的結果表明，一個包含快子的世界將是不穩定的，而自然界中沒有快子的證據。"
        },
        {
          "i": 4,
          "md": "第"
        },
        {
          "i": 5,
          "md": "11"
        },
        {
          "i": 6,
          "md": "廣義相對論的彎曲時空"
        },
        {
          "i": 7,
          "md": "本部分介紹重力即彎曲時空幾何的概念。發展描述彎曲時空的工具，以及在這些彎曲幾何中探測的試驗粒子與光線的運動方程。探討球對稱星體外部、球對稱黑洞、重力波與宇宙學的幾何。描述廣義相對論的基本檢驗。"
        }
      ]
    },
    {
      "num": "7",
      "body": [
        {
          "i": 0,
          "md": "[C] 一個粒子沿 $x$ 軸運動，在其瞬時靜止系中測量的加速度始終為常數 $g$，即均勻加速。假設粒子在 $t = 0$ 時以零速度經過 $x_0$，求 $x$ 和 $t$ 作為固有時 $\\tau$ 的函數。在時空圖上畫出粒子的世界線。"
        }
      ]
    },
    {
      "num": "8",
      "body": [
        {
          "i": 0,
          "md": "[S] 一個 $\\pi^{0}$ 介子（靜質量 135 MeV）以速度（三速度的大小）$V = c/\\sqrt{2}$ 沿與 $x$ 軸成 $45^{\\circ}$ 方向運動。"
        },
        {
          "i": 1,
          "md": "(a) 求粒子四速度的分量。\n\n(b) 求能量-動量四向量的分量。"
        }
      ]
    },
    {
      "num": "9",
      "body": [
        {
          "i": 0,
          "md": "[S] 在已退役的史丹佛直線對撞機（Stanford Linear Collider）中，電子和正電子在一根 2 英里長、直徑僅幾公分的束管中被加速到約 40 GeV 的能量。在如此長的距離上將電子引導通過如此狹窄的路徑，聽起來是艱鉅的任務。但當電子具有這一能量時，加速器在電子靜止系中有多長？"
        }
      ]
    }
  ]
}