{
  "title": "相對論星體",
  "body": [
    {
      "i": 0,
      "md": "大多數恆星靠熱氣體的壓力來抵抗重力的塌縮。在穩定狀態下，輻射所損失的能量由熱核反應提供，這些反應將原子核結合並釋放能量。例如，我們太陽的能量主要來自四個氫核（四個質子）結合成一個氦核的反應所釋放的能量。"
    },
    {
      "i": 1,
      "md": "如 Chapter 12 所述，恆星核心最終可能耗盡熱核燃料。之後它可能演化至兩種終態之一：（1）持續的重力塌縮，導致黑洞；（2）由非熱壓力源支撐對抗重力的恆星。第一種可能性——塌縮為黑洞——已在 Chapter 12 中描述。本章回到第二種可能性，即自然界中實現的白矮星與中子星。"
    },
    {
      "i": 2,
      "md": "與黑洞不同，黑洞完全可以在廣義相對論的框架內理解；而理解恆星演化終態的恆星幾乎需要其餘所有物理學的知識。例如，地球（以及桌椅等普通物體）抵抗重力所依賴的最簡單非熱壓力形式，涉及對固體性質的理解。這正是本章安排在書末的原因。"
    },
    {
      "i": 3,
      "md": "為了更具體地說明這一點，想像從中子星表面鑽至其核心。在一片氫氦海洋之下，有一層固態地殼，其性質由原子間的量子電子力決定。這些力與決定普通固體性質的力相同，但這裡的密度遠超地球上任何可得的密度。"
    },
    {
      "i": 4,
      "md": "繼續向下挖掘，我們進入一個物質性質由 Pauli 不相容原理決定的區域，該原理作用於相對論性電子，這些電子透過弱相互作用與質子和中子保持平衡。這些核子被束縛在富含中子的原子核中，這在地球上自然界中找不到。"
    },
    {
      "i": 5,
      "md": "再向深處挖掘，我們進入幾乎所有電子都已消失的區域。原子核已溶解，形成超流態核物質，其性質由強相互作用決定，但這裡的密度已超過普通原子核的密度，也超過地面實驗室所能達到的密度。"
    },
    {
      "i": 6,
      "md": "這段從表面到中心的旅程，穿越了凝聚態物理學、相對論統計力學、弱相互作用物理學、核物理學和強相互作用物理學各自居中心地位的區域。量子力學貫穿始終，而重力將一切聯繫在一起。"
    },
    {
      "i": 7,
      "md": "我們無法在本書中對理解恆星演化平衡終態所需的整個物理學範疇進行回顧。然而，由於一個核心事實，我們可以孤立引力物理學的本質作用，並討論這些恆星的整體結構：引力是唯一的長程力。支配物質性質的力都是短程力。例如，核力的作用範圍約為 $10^{-13}$ cm；典型中子星的半徑約為 10 km；白矮星甚至更大。電磁力對帶有淨電荷的物質可以是長程的。但構成中子星和白矮星的物質是電中性的，因此長程電磁力被有效地屏蔽。"
    },
    {
      "i": 8,
      "md": "這種作用範圍的差異意味著，在極好的近似下，與中子星和白矮星整體結構相關的物質性質，可以用一個聯繫理想流體壓力 $p$ 與其能量密度 $\\rho$ 的物態方程來概括。因此，理解恆星演化平衡終態的任務可以分為兩部分：（1）計算熱核演化終態物質的物態方程；（2）計算由這種物質構成的恆星如何被重力維繫在一起。在下文中，我們僅報告（1）的結果，但推導（2）。我們從最簡單的非熱壓力源例子開始。"
    },
    {
      "i": 9,
      "title": "Pauli 原理的威力"
    },
    {
      "i": 10,
      "md": "非熱壓力的一個簡單但非常重要的例子，是源自 Pauli 不相容原理的 Fermi 壓力。Pauli 原理限制了半整數自旋粒子（如電子、質子和中子，統稱為費米子）允許的量子態。Pauli 原理禁止任何兩個費米子佔據同一量子態。Pauli 原理對原子結構及其化學性質至關重要。其具體後果是，在原子的最低能量狀態中，電子並不位於靠近原子核的最低能級；相反，它們排列在較高能級的殼層中。實際上，Pauli 原理使原子中的外層電子抵抗原子核吸引電力的作用。我們將看到 Pauli 原理如何能夠支撐一顆恆星抵抗引力的吸引。"
    },
    {
      "i": 11,
      "md": "為了理解 Pauli 原理的運作，想像一盒自旋 $\\frac{1}{2}$ 的費米子氣體。假設費米子處於絕對零度，使得氣體處於可能的最低能量狀態。這樣的費米子氣體稱為退化氣體。即使在零溫度下，即使費米子之間沒有相互作用勢，也存在源自 Pauli 原理的壓力。基本思路可以在一維情況下理解。$^{1}$"
    },
    {
      "i": 12,
      "md": "首先，考慮一個質量為 $m$ 的單個費米子在一維箱子中運動的狀態，該箱子從 $x = 0$ 延伸到 $x = L$，如 Figure 24.1 所示。為簡單起見，暫時假設費米子是非相對論性的。箱中可能的能級是量子化的。"
    },
    {
      "i": 13,
      "caption": "FIGURE 24.1 一維長度為 $L$ 的箱子中包含八個無相互作用費米子的能級。單粒子可用的能級是離散的。八個費米子的最低能量狀態是：兩個自旋相反的費米子位於最低能級，兩個位於次低能級，依此類推。這是八個粒子中不存在任何兩個費米子佔據同一態（如 Pauli 不相容原理所要求）的最低能量構型。若箱中的粒子不遵循不相容原理，最低能量狀態則會讓所有八個費米子位於最低單粒子能級。"
    },
    {
      "i": 15,
      "md": "其中 $p_{k}$ 是動量的大小，等於"
    },
    {
      "i": 17,
      "md": "無論粒子是否相對論性，這些結果都是允許的動量值。"
    },
    {
      "i": 18,
      "md": "含有一個粒子的箱子的最低能量狀態，是將該粒子置於最低單粒子能量本徵態 $k = 1$ 中。但含有 $N$ 個粒子的箱子的最低能量狀態必須考慮 Pauli 原理。為簡便起見，假設 $N$ 為偶數，並想像一次向箱中填入一個粒子，將新增的粒子置於最低可用的單粒子能量本徵態。自旋 $\\frac{1}{2}$ 粒子有兩種可能的自旋態。前兩個粒子可以放入最低能量（$k = 1$）單粒子態，但接下來的兩個必須進入次高（$k = 2$）單粒子態，以此類推。包含最後兩個粒子的最高已填態的動量大小，稱為 Fermi 動量 $p_{F}$。因此，含有 $N$ 個粒子的箱子的最低能量狀態具有總能量"
    },
    {
      "i": 20,
      "md": "對於實際氣體或恆星中可能出現的非常大的 $N$ 值，如 (24.3) 中的求和可以用積分代替。將它們寫成對動量大小 $p$ 從 0 到 $p_{F}$ 的積分較為方便。Eq. (24.2) 表明，動量 $p$ 每間隔 $\\pi\\hbar/L$ 就有一個態。因此，對於感興趣的求和，"
    },
    {
      "i": 22,
      "md": "對任意函數 $F(p)$ 而言。因子 $(\\mathcal{L}/\\pi\\hbar)$ 因此是動量大小方向的態密度。"
    },
    {
      "i": 23,
      "md": "我們生活在三維空間中，而非一維。在邊長為 $L$ 的立方箱中自由運動的粒子的能量本徵態，可由動量三個分量的大小 $(p^{x}, p^{y}, p^{z})$ 來表徵，每個分量按類似 (24.2) 的規則量子化。在 $p^{x}$、$p^{y}$ 和 $p^{z}$ 正值張成的三維動量空間中，態密度為 $(\\mathcal{L}/\\pi\\hbar)^{3}$。在 $N$ 個費米子系統的最低能量狀態中，所有這些態被填充至某一動量空間半徑 $p_{F}$。"
    },
    {
      "i": 24,
      "md": "我們可以立即通過求出 $N$ 個費米子氣體的 Fermi 動量 $p_{F}$ 來說明這些概念。總數 $N$ 必須是動量空間球半徑 $p_{F}$ 內所有正 $p^{\\lambda}$、$p^{\\lambda}$、$p^{\\bar{\\lambda}}$ 態數量的兩倍："
    },
    {
      "i": 26,
      "md": "其中，正 $p$ 的動量空間八分之一的積分已被寫為整個球面積分的八分之一。這給出了數密度 $n = \\mathcal{N} / \\mathcal{L}^3$ 與 $p_F$ 之間以下關係："
    },
    {
      "i": 28,
      "md": "若引入 Fermi 波長 $\\lambda_{F} \\equiv 2\\pi\\hbar/p_{F}$，數密度可寫為 $n = 8\\pi/3\\lambda_{F}^{3}$，表明每個費米子被限制在特徵尺寸為 $\\lambda_{F}$ 的體積內。這正是我們在 Box 12.1 第 257 頁估算由 Fermi 壓力支撐的恆星最大質量時所用的關係。我們稍後將提供這一最大質量更定量的推導。"
    },
    {
      "i": 29,
      "md": "類似地，氣體的能量密度 $\\rho$ 可以通過在 (24.5) 的積分中加入能量作為動量的函數——$E(p) = (m^{2}c^{4} + p^{2}c^{2})^{1/2}$——的權重來計算。（保留 $c$ 的因子以便與你可能見過的其他公式進行比較。）結果將取決於積分上限 $p_{F}$，但可以利用 (24.6) 用 $n$ 重新表達。這個積分並不困難，在非相對論極限（$E(p) \\approx mc^{2} + p^{2}/2m$）和極端相對論極限（$E(p) \\approx pc$）下尤為簡單。在這些極限下"
    },
    {
      "i": 32,
      "md": "為了計算壓力，我們可以在零溫度下使用熱力學第一定律。這將箱中總能量的變化 $\\Delta E$ 與體積的微小變化 $\\Delta V$ 相關聯，保持費米子數 $N$ 固定。具體地，"
    },
    {
      "i": 34,
      "md": "其中 $p$ 是壓力。（注意不要將壓力的 $p$ 與動量的 $p$ 混淆——兩種記號都是標準的。）注意到 $E = \\rho V$ 且 $V = N n$。"
    },
    {
      "i": 36,
      "md": "退化費米子的物態方程"
    },
    {
      "i": 37,
      "md": "這給出 $p = n(d\\rho / dn) - \\rho$，結合 (24.7)，得到"
    },
    {
      "i": 40,
      "md": "可以通過消去 (24.7) 中能量密度 $\\rho$ 的表達式與 (24.9) 中壓力表達式之間的數密度 $n$，來得到零溫度非相互作用費米子的物態方程 $p = p(\\rho)$。結果以圖形方式呈現在 Figure 24.2 中。在下文中，我們將用這個簡單的物態方程來說明這種非熱壓力源如何能夠被相對論性重力的吸引力所平衡，從而給出一族平衡恆星。"
    },
    {
      "i": 41,
      "title": "相對論流體靜力學平衡"
    },
    {
      "i": 42,
      "md": "本節展示決定相對論性恆星在重力壓縮力與抵抗壓縮的壓力之間平衡的結構方程。我們假設已給定一個物態方程 $p = p(\\rho)$，例如上一節所描述的那個。"
    },
    {
      "i": 43,
      "md": "為簡便起見，我們只研究非自轉、球對稱的恆星。恆星外部的幾何由熟悉的 Schwarzschild 度規 (9.9) 描述，"
    },
    {
      "i": 45,
      "md": "其中 $M$ 是恆星的總質量。然而，為了確定恆星的結構，還需要內部的度規。"
    },
    {
      "i": 46,
      "md": "Example 21.4 表明，可以選擇座標 $(t, r, \\theta, \\phi)$，使得任何球對稱、與時間無關的度規可以化為以下形式"
    },
    {
      "i": 48,
      "md": "對某些僅依賴於 $r$ 的函數 $v(r)$ 和 $\\lambda(r)$ 而言。Schwarzschild 度規具有此形式。這種形式的度規在恆星內部和外部均成立。"
    },
    {
      "i": 49,
      "md": "我們假設構成恆星的物質是一種完美流體，具有 Section 22.2 中描述形式的應力-能量張量。(22.39) 中給出的應力-能量取決於能量密度 $\\rho$、流體壓力 $p$ 和流體四速度 $\\mathbf{u}$。由於恆星物質是靜態的，$\\mathbf{u}$ 的空間部分消失，歸一化的 $\\mathbf{u}$ 具有形式 $u^{\\alpha} = (e^{-v/2}, \\vec{0})$。壓力通過物態方程 $p = p(\\rho)$ 與密度相聯繫。在本章幾乎全程使用的幾何單位中，壓力和能量密度的單位都是長度的倒數平方（參見第 479 頁的討論）。"
    },
    {
      "i": 50,
      "md": "度規與物質之間共有三個未知函數需要由 Einstein 方程求解——$\\nu(r)$、$\\lambda(r)$ 和 $\\rho(r)$。我們不逐一寫出 Einstein 方程 $G_{\\alpha\\beta} = 8\\pi T_{\\alpha\\beta}$ 的各分量。而是展示三個獨立方程，它們由以各種方式組合這些方程得出（見 Problem 4）。我們從一個有用的重新定義開始："
    },
    {
      "i": 52,
      "md": "這只是用另一個待定函數 $m(r)$ 替換了一個待定函數 $\\lambda(r)$。新函數 $m(r)$ 在恆星外部具有恆定值——即其總質量 $M$。$m(r)$、$\\rho(r)$ 和 $\\nu(r)$ 的三個方程為"
    },
    {
      "i": 54,
      "md": "其中，$p$ 始終理解為通過物態方程與 $\\rho$ 相關聯。這三個方程統稱為球形相對論性恆星的結構方程。我們將在下一節中看到它們如何決定恆星內部的壓力、密度和幾何分布。"
    },
    {
      "i": 55,
      "md": "為了更好地理解這些方程，考察其非相對論極限是有啟發性的。按 Appendix A 中的方式恢復 $G$ 和 $c$ 的因子，得"
    },
    {
      "i": 57,
      "md": "在非相對論極限下，靜質量密度 $\\mu c^{2}$ 主導能量密度 $\\rho$。將 (24.11) 與靜態弱場度規 (6.20) 比較，表明在該極限下 $v(r)$ 變為 $2\\Phi(r)/c^{2}$，其中 $\\Phi(r)$ 是恆星內部的 Newton 引力勢。將這些結果代入結構方程 (24.13)，並取 $1/c$ 的最低階，得到非相對論極限為"
    },
    {
      "i": 61,
      "md": "球形相對論性恆星的結構方程"
    },
    {
      "i": 62,
      "caption": "FIGURE 24.3 球形恆星內部一個小流體元上的壓力。流體元在徑向方向的尺寸為 $\\Delta r$，在垂直於 $r$ 的方向面積為 $\\Delta A$。外表面的徑向壓力為 $-p(r + \\Delta r)\\Delta A$。內表面的壓力為 $+p(r)\\Delta A$。指向徑向的淨壓力為 $-p(r + \\Delta r)\\Delta A + p(r)\\Delta A = -(dp/dr)\\Delta V$，其中 $\\Delta V = \\Delta A\\Delta r$ 是流體元的體積。在流體靜力學平衡中，這個淨壓力將由指向中心的重力吸引所平衡。"
    },
    {
      "i": 63,
      "md": "第一個方程確定半徑 $r$ 以內的靜質量 $m(r)$，以靜質量密度 $\\mu(r)$ 表示。下一個方程表達平衡恆星中壓力與重力之間的平衡。為說明這一點，考慮位於半徑 $r$ 處的一個小立方體積 $\\Delta V$（見 Figure 24.3）。該體積沿半徑方向有一個大小為 $\\Delta r$ 的邊；垂直於半徑的兩個面構成面積 $\\Delta A$。指向外側的淨壓力是兩個橫截面上壓力的差值："
    },
    {
      "i": 65,
      "md": "這必須與體積中質量所受的向內重力平衡："
    },
    {
      "i": 67,
      "md": "這個平衡就是 (24.15b) 的內容。當乘以體積中的質量時，(24.15c) 將由引力勢推導出的重力與由 Newton 球形天體定理推導出的重力等同起來（回顧 Example 3.1）。接受 Newton 定理，這可以視為引力勢的定義。"
    },
    {
      "i": 68,
      "md": "廣義相對論方程 (24.13) 具有大致相同的解釋。第一個方程 (24.13a) 定義了一個量 $m(r)$，它在確定平衡中的行為類似於半徑 $r$ 以內的質量。它不可能精確地是質量，因為雖然存在物質的能量密度，但在廣義相對論中不存在包含重力能量的局部能量密度概念，正如 Section 16.5 中所討論的。儘管如此，表面半徑 $R$ 處 $m(r)$ 的值是外部 Schwarzschild 幾何中的質量 $M$，也是從無窮遠測量到的恆星總質量。Eq. (24.13c) 決定 $\\nu(r)$，從而決定度規分量 $g_{tt}(r)$。Eq. (24.13b) 是相對論流體靜力學平衡方程，表達恆星內部每個小體積上壓力與重力的平衡。"
    },
    {
      "i": 69,
      "md": "比較 (24.13b) 右端與其 Newton 極限 (24.15b)，粗略地說，在廣義相對論中重力吸引比 Newton 的 $m(r)/r^{2}$ 更強。例如，壓力的貢獻增加了 $m(r)$ 和 $\\rho(r)$。分母比 $r^{2}$ 小一個因子 $1 - 2m(r)/r$。這些差異對相對論性恆星有重要影響。"
    },
    {
      "i": 70,
      "title": "恆星模型"
    },
    {
      "i": 71,
      "md": "相對論流體靜力學平衡方程 (24.13) 是一個一階常微分方程組，對於給定的物態方程，可以用標準數值演算法積分。我們現在詳細描述如何進行這一積分。我們首先考慮 (24.13a) 和 (24.13b) 這兩個關於 $m(r)$ 和 $\\rho(r)$ 的方程，它們本身構成一個封閉系統。"
    },
    {
      "i": 72,
      "md": "1. 從恆星中心 $r = 0$ 開始，給定中心密度 $\\rho_c$ 的值。中心壓力 $p_c$ 由物態方程確定：$p_c = p(\\rho_c)$。$m(r)$ 的中心值必須為零；否則時空在中心附近不會是局部平坦的，空間度規也不會具有 $dS^2 = dr^2 + r^2(d\\theta^2 + \\sin^2\\theta d\\phi^2)$ 的形式（Problem 5）。\n\n2. 以這些邊界條件從內向外積分耦合結構方程 (24.13a) 和 (24.13b)。Eq. (24.13b) 表明 $dp/dr < 0$，所以壓力穩定下降，如 Figure 24.4 所示。當 $dp/d\\rho > 0$ 時（如 Figure 24.2），密度也是如此。（實際上，這是任何物態方程的性質，正如 Section 24.6 中所解釋的。）質量 $m(r)$ 穩定上升。最終，達到壓力消失的半徑 $R$，即 $p(R) = 0$。這就是恆星的表面，在此處不需要外部物質的重量來維繫最後一小塊流體。表面處 $m(R)$ 的值就是恆星的總質量 $M$。\n\n3. 對從零到無窮大的所有 $\\rho_{c}$ 值重複這一過程，找出由給定物態方程的物質構成的球形恆星族。這些恆星構成一個以 $\\rho_{c}$ 為參數的單參數族。這些恆星的質量 $M(\\rho_{c})$ 和半徑 $R(\\rho_{c})$ 是 $\\rho_{c}$ 的函數。\n\n4. 為了完成恆星內部時空幾何的計算，可以從表面值 $\\log(1 - 2M/R)$ 向內積分 (24.13c)$^{2}$，以求出內部的 $\\nu(r)$。恆星內部的度規由 (24.11) 給出，其中 $\\nu(r)$ 由此計算確定，$\\lambda(r)$ 由 (24.12) 確定。"
    },
    {
      "i": 74,
      "md": "Chandrasekhar 質量"
    },
    {
      "i": 75,
      "md": "這種計算的結果在 Figure 24.5 中對由等量質子和電子組成的物質的物態方程加以說明。壓力假設由遵循 (24.9) 的退化電子提供。大部分能量密度來自質子的靜能。這近似了實際白矮星內部的物理。存在一個以中心密度 $\\rho_{c}$ 為標籤的單參數恆星族。圖中顯示了該序列中每顆恆星的總質量 $M$ 和 Schwarzschild 座標半徑 $R$。這一計算的一個重要結果是，退化電子的 Fermi 壓力能夠支撐的總質量存在一個上限，約為 $1.4M_{\\odot}$。這就是 Chandrasekhar 質量，其值在 Box 12.1 中已粗略估算。"
    },
    {
      "i": 76,
      "md": "Figure 24.5 中所示的恆星族是對實際白矮星的合理近似。這些恆星並不是非常相對論性的。特徵比值 $GM/c^{2}R$ 最多為千分之幾。然而，退化電子的壓力對恆星演化終態物質的壓力源是一個好的近似，但僅適用於密度低於約 $10^{11}$ g/cm$^{3}$ 的情況。現在我們轉向更高密度和更相對論性的天體。"
    },
    {
      "i": 77,
      "title": "基態物質"
    },
    {
      "i": 78,
      "md": "用於構建 Figure 24.5 所示恆星族的自由退化費米子物態方程，是對問題「$\\mathcal{N}$ 個無相互作用費米子在一個箱中的最低能量狀態（基態）是什麼？」的回答。更一般地，我們要求包含現實力（如在足夠高密度下變得重要的強相互作用和弱相互作用）的物質基態的物態方程。這是一個在理論上更難回答的問題，但涉及的部分物理在 Box 24.1 中有定性描述。由這種現實基態物質構建的球形恆星族，是中心密度高於 $10^{14}$ g/cm$^3$ 的恆星演化終態的良好近似。這些恆星的整體性質（如質量和半徑）幾乎完全取決於高於此密度的物質性質，在此密度下，理想流體是一個好的近似，帶有聯繫壓力和密度的物態方程。"
    },
    {
      "i": 80,
      "md": "通常（也是慣例）用以下量來概括物態方程："
    },
    {
      "i": 82,
      "md": "這是因為一些有用的簡單模型給出 $\\gamma$ 為常數的物態方程。例如，Section 24.1 中討論的退化費米子物態方程，在費米子非相對論性時有 $\\gamma = \\frac{5}{3}$，在它們變為相對論性時平滑過渡到 $\\gamma = \\frac{4}{3}$（Problem 13）。無量綱量 $\\gamma$ 是物態方程剛性的度量。$\\gamma$ 越大，給定能量密度增量對應的壓力增量越大，物態方程越剛硬。"
    },
    {
      "i": 83,
      "md": "BOX 24.1 物質的基態"
    },
    {
      "i": 84,
      "md": "在一個邊長約 1 m 的箱子中，$10^{27}$ 個質子和等量電子的最低能量狀態是什麼？這種最低能量狀態稱為那些條件下物質的基態。基態將是零溫度，因此沒有熱運動能量。電子將與原子核結合形成原子，原子將結合在一起形成固體。但基態並非由 $10^{27}$ 個氫原子構成。質子可以與電子結合形成中子，質子和中子可以結合形成原子核，這比它們各自分開具有更強的束縛（更低的能量）。不管使這些轉變所必需的核反應如何發生；我們正在研究一個原則性問題。每核子質量最低的原子具有 ${}^{56}$Fe 原子核。這主要是因為 ${}^{56}$Fe 接近於束縛能最大的原子核（見 Figure 12.1 中束縛能相對核子數的曲線）。因此，$10^{27}$ 個質子和等量電子的初始構型的基態，是一塊零溫度的固態 ${}^{56}$Fe。由於鐵在低壓下的密度約為 $\\sim 79~\\text{g cm}^3$，這塊固體邊長約為 20 cm，在零壓下可以放入 1 m 的箱子中。"
    },
    {
      "i": 85,
      "md": "現在想像將箱子縮得越來越小（最終壓縮鐵），以求出較高密度下的基態。縮小箱子的速度要慢於冷卻時間，使其持續保持在零溫度，所有可能發生的核反應都會發生。能量密度 $\\rho$ 將上升，壓力 $p$ 也隨之上升。這樣我們可以想像在所有密度下確定基態物質的物態方程 $p = p(\\rho)$。該物態方程的主要特徵在下面的討論中有定性描述。定量計算結果以 (24.18) 中定義的剛性參數 $\\gamma$ 總結在 Figure 24.6 中。"
    },
    {
      "i": 86,
      "md": "最低密度下，基態由束縛成固體的原子構成，對實際恆星的整體結構並不重要，原因有二：第一，以單個原子描述物質的方式僅在此類恆星表面附近的微小區域內有效。第二，基態物質並非白矮星和中子星實際表面條件的現實近似。因此，我們可以安全地從物理更簡單的較高密度開始討論。"
    },
    {
      "i": 87,
      "md": "隨著箱中物質被壓縮至更小的體積，內部電子的能量上升——其動量 $p$ 大致隨 $p \\sim \\hbar/\\lambda$ 變化，其中 $\\lambda$ 是典型電子被限制體積的大小 [參見 (24.2)]。到密度約 $\\rho \\sim 10^{4}$ g/cm$^{3}$ 時，電子不再束縛在原子中。壓力的主要來源是由 Pauli 原理引起的這種近似自由電子氣體的 Fermi 壓力，如 Section 24.1 所述。能量密度在極好的近似下是原子核的靜能。"
    },
    {
      "i": 88,
      "md": "剛性參數 $\\gamma$ 對非相對論性電子氣體從 5/3 開始，當電子在約 $\\rho \\sim 10^{6}$ g/cm$^{3}$ 時變為相對論性（能量 $\\sim m_{e}c^{2}\\sim .5$ MeV）時下降到 4/3。在略高於 $\\rho \\sim 10^{6}$ g/cm$^{3}$ 時，典型電子能量達到中子-質子質量差（$m_{n}c^{2}-m_{p}c^{2}=1.3$ MeV）。大致在那個能量下，束縛在原子核中的質子吸收一個電子並通過弱相互作用 $e^{-}+p\\rightarrow n+\\nu$ 變成中子，在能量上變得更為有利。隨著電子消失，原子核變得越來越富含中子和貧乏質子，物態方程變軟。在約 $4\\times10^{11}$ g/cm$^{3}$ 的密度下，物質變得如此富含中子，以至於能量最高的中子從原子核中解離出來。這一現象稱為中子滴流，$\\gamma$ 急劇下降，因為壓縮能量用於釋放中子而非提供壓力。"
    },
    {
      "i": 89,
      "md": "隨著壓縮繼續進行，原子核之間的中子密度增加，最終等於原子核內部的中子密度。原子核隨即合併，形成一種主要由中子組成、含少量質子和足夠電子以確保電中性的均勻流體。這就是構成中子星的主要物質——中子物質。"
    },
    {
      "i": 90,
      "md": "在此區域，中子被緊密堆積在一起，分離距離可與核（強相互作用）力作用範圍 $10^{-13}$ cm 相比，並最終小於後者。這些強相互作用力現在取代電子，成為壓力的主要來源，而電子基本上已消失。"
    },
    {
      "i": 91,
      "md": "在這些區域計算物態方程並非易事。核子（質子和中子）系統是強耦合的；在更高密度下它完全是相對論性的，並與其他基本粒子耦合，如 $\\pi$、$\\Lambda$、$\\Delta$、K 等。Figure 24.6 顯示了一種計算的結果。基本的定性特徵是 $\\gamma$ 隨能量密度穩步上升，這是核力排斥部分的結果，使得物態方程越來越剛硬，直至遠超核密度。"
    },
    {
      "i": 93,
      "md": "Figure 24.6 中顯示了基態物質密度的 $\\gamma$ 函數的一個計算結果。使用此物態方程按上一節描述的方式積分相對論結構方程，所得球形恆星族在 Figure 24.7 中顯示。$^{3}$ 在密度高於約 $10^{14}$ g cm$^{3}$ 時，幾乎所有電子都已與質子結合形成中子：因此，高於此中心密度的恆星稱為中子星。強相互作用對其性質很重要，因此最高密度下的計算結果有一定的不確定性。儘管如此，幾個重要特徵清晰呈現。首先，這些恆星非常緊緻，質量約為一個太陽質量，半徑約為 10 km。提供壓力的中子質量大約是提供白矮星壓力的電子質量的 1000 倍，中子星半徑大約小 1000 倍（Problem 14）。其次，由於 $GM/Rc^{2} \\sim .1$，相對論性重力對中子星結構很重要。第三，即使是排斥性強相互作用力也不足以支撐任意數量的基態物質抵抗重力；"
    },
    {
      "i": 94,
      "md": "$^{3}$ 在密度低於 $10^{11}$ g/cm$^{3}$ 時，Figure 24.7 在細節上與 Figure 24.5 不同。這是因為，雖然在兩種情況下退化電子都提供壓力，但在實際白矮星中，降低能量至基態所需的核反應並未發生。在 Figure 24.4 和 Figure 24.7 中對原子核靜能的假設不同。"
    },
    {
      "i": 96,
      "md": "基態物質無法抵抗重力而存在最大中子星質量，約為幾個太陽質量。這一最大質量用於區分中子星與黑洞，如 Section 13.1 所述。然而，並非 Figure 24.7 中顯示的所有恆星都能在自然界中存在，因為並非所有恆星都是穩定的。因此，我們現在轉向穩定性問題。"
    },
    {
      "i": 97,
      "title": "穩定性"
    },
    {
      "i": 98,
      "md": "一顆恆星要在自然界中存在，僅僅處於平衡狀態是不夠的。它必須是穩定的平衡。"
    },
    {
      "i": 99,
      "md": "Figure 24.8 回顧了經典力學中一個質量為 $m$ 的粒子在一維勢 $V(x)$ 中運動的穩定和不穩定平衡概念。勢的極大值和極小值是粒子所受力消失的平衡位置。勢的極小值，如 Figure 24.8 中的 A，是穩定平衡。給一個靜止於此的粒子稍多一點能量，它將圍繞該平衡振盪，若額外能量很小則永遠不會偏離太遠。偏離平衡的小位移 $\\xi(t)$ 將遵從通過在 $\\xi$ 中展開運動方程 $m\\ddot{x} = -dV/dv$ 並只保留最低階項而得到的運動方程。即"
    },
    {
      "i": 102,
      "md": "這個方程的解像 $\\xi(t) \\propto \\exp(\\pm i\\omega_{1}t)$ 一樣諧和變化（當然只有實部給出位移），其中"
    },
    {
      "i": 104,
      "md": "由於 A 是極小值，$\\omega_{A}^{2}$ 為正，$\\omega_{A}$ 為實數，解將以有界振幅振盪。這就是穩定性。"
    },
    {
      "i": 105,
      "md": "相反，勢的極大值（如 Figure 24.8 中的 B）是不穩定平衡。給靜止於此的粒子一點額外能量，它將越來越遠地偏離平衡。更明確地說，類比 (24.20) 定義的 $\\omega_{B}^{2}$ 將為負，$\\omega_{B}$ 將為虛數。因此，(24.19) 的解將表現為 $\\xi \\propto \\exp(\\pm |\\omega_{B} t)|$——一個隨時間增長，另一個衰減。一支鉛筆豎立在筆尖是不穩定平衡及這類運動的簡單例子。有一種衰減運動，鉛筆緩慢滑向垂直位置並停止，保持平衡。但現實中的鉛筆會受到不可控擾動（例如氣流）的影響，同時產生增長和衰減運動。任何增長的擾動，無論初始多小，最終都會超過衰減的擾動，鉛筆將倒下。一個單一的增長擾動就足以證明一個力學系統的不穩定性。"
    },
    {
      "i": 106,
      "caption": "FIGURE 24.9 固定端振動弦的兩個簡正模式。圖中繪出了 (24.24) 中明確給出的長度為 $L$ 的振動弦最低兩個模式的振幅 $\\xi_{n}(x)$。"
    },
    {
      "i": 107,
      "md": "恆星穩定性的分析在定性上類似；唯一真正的區別是恆星有更多可能的振盪模式。這些可以分解成具有確定頻率的簡正模式。如果其中甚至一個頻率的平方為負，恆星就將不穩定，並在自然界中無法存在。$^{4}$"
    },
    {
      "i": 108,
      "md": "實際上需要對平衡附近的小振盪求解 Einstein 方程，才能計算恆星的簡正模式並求出其頻率。這一計算並不太困難，但它提供的信息遠多於僅回答恆星是否穩定這一問題所需。為此，只需要幾個關於模式的一般事實——事實上，這些事實與許多類似振動系統（如弦和鼓）共同具備。我們現在從 Example 24.1 中簡單的振動弦案例開始描述這些事實。"
    },
    {
      "i": 109,
      "md": "Example 24.1. 振動弦。振動弦的簡單例子提供了與相對論性恆星小振盪的一些有益類比。想像一根弦拉伸在兩個相距 $L$ 的固定端點之間，如 Figure 24.9 所示。弦的張力為 $T$，其線質量密度為 $\\sigma$。"
    },
    {
      "i": 110,
      "md": "拉直的弦是一種平衡構型——不隨時間改變——類比於相對論性恆星的平衡。若弦被撥動，它將以振幅 $\\xi(t,x)$ 振動，該振幅滿足波動方程 $^{5}$"
    },
    {
      "i": 112,
      "md": "相對論性恆星徑向振盪的方程在性質上相似，但更為複雜。弦的正規模是 (24.21) 的解，具有諧和時間依賴性 $\\xi(t) \\propto \\exp(\\pm i\\omega t)$。固定端邊界條件只能在離散的頻率譜下被滿足"
    },
    {
      "i": 114,
      "md": "$^{4}$ 在某些情況下，不穩定性的時間尺度可能非常長，使得恆星確實能在天文物理上具有意義的時間內存活。但這類久期不穩定性並不在我們即將分析的球形模之中。\n\n$^{5}$ 若以下標準討論中有任何不熟悉之處（包括此式），請複習你的基礎力學教材，或完成 Problem 15。"
    },
    {
      "i": 115,
      "md": "在此頻率下，整數個半波長恰好能夠填入兩端之間。對應的正規模為"
    },
    {
      "i": 117,
      "md": "其中"
    },
    {
      "i": 119,
      "md": "對於某個常數複振幅 $A_{n}$。頻率標記方式使得第 $n$ 個模有 $n$ 個節點（不計兩端）。"
    },
    {
      "i": 120,
      "md": "只要 $T$ 為正，對於任何偏離直線平衡態的位移都存在回復力，所有模的頻率平方均為正，平衡態是穩定的。但試想若 $T$ 可以變為負值，使壓縮張力變成膨脹力，如同被兩端壓縮的彈簧。直線構型仍是平衡態，但現在最微小的擾動都會增長。由 $(24.22)$ 得到的頻率平方現在全為負，所有模皆不穩定。隨著 $T$ 從正值變為負值，直線構型從穩定平衡過渡到不穩定平衡。"
    },
    {
      "i": 121,
      "md": "事實上，流體位移純為徑向的模控制著球形恆星的穩定性。因此，我們聚焦於流體運動沿徑向進出的這些徑向模。與振動弦頗為相似，球形振盪由未受擾動恆星中位於半徑 $r$ 處的流體元素的徑向位移 $\\xi(r,t)$ 作為時間的函數來描述。可能的位移可以分解為具有確定頻率 $\\omega_{n},\\ n = 0, 1, 2, 3$ 的離散正規模譜。在每個模中，位移為"
    },
    {
      "i": 123,
      "md": "穩定模具有 $\\omega_{n}^{2}>0$，頻率為實數，且做振盪。不穩定模具有 $\\omega_{n}^{2}<0$，頻率為虛數，且能在時間上指數增長。無論其行為如何，這些模都守恆能量。啟動它們需要一點能量，但之後該能量守恆。幾個最低模的模函數 $\\xi_{n}(r)$ 示意性地展示於 Figure 24.10 中。這些模在中心處必須消失，因為中心在振盪過程中保持固定。在表面，它們必須保持壓力在那裡消失的條件。最低頻模除中心的節點外沒有其他節點。第 $n$ 個模有 $n$ 個節點。"
    },
    {
      "i": 124,
      "md": "設想已對 Figure 24.7 所示的單參數恆星族中每顆恆星的正規模頻率進行了計算，使用基態物質的物態方程。結果是每個正規模 $\\omega_{n}^{2}(\\rho_{c})$，$n = 0,1,2,\\ldots$，作為參數化該族的中心密度 $\\rho_{c}$ 的函數。Figure 24.11 示意性地展示了 $\\omega_{n}^{2}(\\rho_{c})$ 對 $\\rho_{c}$ 的曲線可能的形貌"
    },
    {
      "i": 126,
      "md": "隨著 $\\rho_{c}$ 的變化，各模的頻率平方也隨之改變，模可以從穩定變為不穩定，反之亦然。第 $n$ 個模在某個中心密度處從穩定變為不穩定，此時 $\\omega_{n}^{2}$ 從正值變為負值；從不穩定變為穩定則是反向的變化。無論哪種情況，一個模在改變穩定性時具有零頻率。但零頻率模是特殊的，它是一個不隨時間改變的位移。"
    },
    {
      "i": 128,
      "md": "它是從一個平衡構型到另一個平衡構型的位移——即沿 Figure 24.7 所示的 $M(R)$ 曲線的位移。"
    },
    {
      "i": 129,
      "md": "對應於零頻率模的位移不能在平衡構型序列上的任意位置發生。零頻率模的能量為零，因此位移必須守恆總質量-能量。零頻率模——從而穩定性的改變——只能發生在 $M$ 對 $R$ 曲線的極值點，在那裡質量對改變 $R$ 的小位移的一階修正為零。反之，在任何極值點都存在守恆能量的各平衡態之間的不隨時間改變的位移。零頻率模與極值點因此是一一對應的。恆星演化平衡終態族的穩定性，因此可以完全從 Figure 24.7 中的 $M$ 對 $R$ 曲線加以分析，如我們現在所展示。"
    },
    {
      "i": 130,
      "md": "從低中心密度 $\\rho_{c}$ 開始，在此處平衡構型可被假定為穩定（所有模的頻率平方均為正），並追蹤各模隨增加的 $\\rho_{c}$ 如何改變穩定性，如 Figure 24.11 所示。穩定性第一次發生改變的極值點是 $M(R)$ 的峰值，即 Figure 24.7 中標記為 A 的點。在那裡，最低模變得不穩定。中心密度低於 A 的恆星構成一個穩定的族，在這個範圍的大部分區間由簡併電子的 Fermi 壓力支撐，定性上與 Figure 24.5 中的恆星相似。"
    },
    {
      "i": 131,
      "md": "中心密度高於 A 但低於下一個極值點（B 點的極小值）的恆星是不穩定的，不會在自然界中存在。B 點的零模有兩種可能：（1）最低模可以恢復穩定，或（2）如 Figure 24.11 所示，第二個模與第一個模一同變得不穩定。我們可以通過兩個不同的模如何改變恆星半徑來判斷哪種情況發生。"
    },
    {
      "i": 132,
      "md": "考慮一個零頻率模，其沿平衡構型族的位移增大中心密度。模函數 $\\xi(r)$ 在 $r = 0$ 附近因此必須為負（壓縮）。因此，除 $r = 0$ 外沒有節點的最低模，在表面必須為負，對應於恆星半徑 $R$ 的減小（見 Figure 24.10）。相比之下，具有一個節點的第二個模將增大 $R$。但我們從 Figure 24.7 觀察到，在 B 點，半徑 $R$ 隨中心密度的增大而增大。因此，改變穩定性的不是最低模，而是次低模（有一個節點），它正如 Figure 24.11 所示變得不穩定。沿著這種分析（Problem 16），我們發現唯一另一個穩定區域是從極小值 D 到極大值 E。這些恆星的中心密度約為 $1.2 \\times 10^{14}$ g/cm$^{3}$ 到 $3 \\times 10^{15}$ g/cm$^{3}$。這些由 Box 24.1 中描述的中子物質構成的恆星稱為中子星。"
    },
    {
      "i": 133,
      "md": "中子星是廣義相對論性天體，$GM\\ c^{2}R \\sim .1$（見 Figure 24.7）。對 $3 \\times 10^{15}$ g/cm$^{3}$ 以上的物態方程進行理論外推，沒有進一步穩定恆星族的證據。因此，中子星和白矮星是恆星演化的兩種可能的穩定平衡終態。白矮星可以從其光學性質被探測到；中子星可以從脈衝星現象等手段被探測到（見 Box 24.2）。"
    },
    {
      "i": 134,
      "md": "BOX 24.2 脈衝星"
    },
    {
      "i": 135,
      "md": "脈衝星的觀測特徵是一系列持續的短無線電頻率電磁輻射脈衝，平均間隔精確的週期，典型值約為一秒。這些無線電訊號來自旋轉的、磁化的中子星。"
    },
    {
      "i": 136,
      "md": "中子星在超新星坍縮形成時很容易繼承足夠的角動量，使其每秒自轉一圈。即使以這個速率，它們也不算快速自轉，因為離心力遠小於重力（Problem 18）。緻密的自轉太陽質量天體使其成為非常精確的時鐘。隨中子星旋轉的窄束信標，其光束掃過地球時可以產生觀測到的脈衝。但產生這種光束的機制是什麼？"
    },
    {
      "i": 137,
      "md": "中子星在形成時不僅繼承了角動量，也繼承了磁場。中子星物質具有高度導電性，導電性之高使得任何穿過物質的磁"
    },
    {
      "i": 139,
      "md": "場將在遠長於脈衝星年齡的時間內被凍結。在坍縮過程中，磁通量在導電物質內部近似守恆，幾高斯的普通恆星磁場可以在壓縮下被放大到 $10^{12}$ 高斯。因此，旋轉的中子星可以高度磁化。距恆星遙遠的觀察者會將其視為一個旋轉的磁偶極矩。如果磁矩如圖所示不與旋轉軸對齊，那麼由於旋轉，它將隨時間變化，並輻射出電磁波。這些波帶走的能量使恆星自轉減慢。脈衝星是如此精確的時鐘，以至於其轉動週期的微小減小可以被測量到，且與如此大的磁場值相符。"
    },
    {
      "i": 140,
      "md": "同樣的磁場是圍繞中子星的電漿的來源。在高度導電的內部，旋轉的磁場產生電場。在穩態下，電子所受的力必須近似消失，使得 Lorentz 力定律中的兩項必須相消——$\\vec{E} = -\\vec{V}/c \\times \\vec{B}$，其中 $\\vec{V} = \\vec{\\Omega} \\times \\vec{r}$，$\\vec{\\Omega}$ 是恆星的角速度。電場的切向分量必須跨越恆星表面連續。這意味著恆星外部將存在電場，一般也具有垂直於表面的分量。這個場足夠強，能將電子從原子中拉出並形成一個隨恆星旋轉的電漿。電漿中的帶電粒子沿圖中所示的開放磁力線向外流動，並沿閉合磁力線被束縛。被束縛的粒子隨中子星旋轉，直到距旋轉軸速度等於光速的距離處。無線電脈衝的發射機制目前仍不完全清楚，但一種想法是電漿中的不穩定性可能形成電荷集中，由於旋轉而相干輻射。Chapter 5.5 中討論的相對論性束射效應自然會產生窄束，這可以是觀測到的信標。這樣，中子星以許多方式成為極端條件下物理學的天然實驗室。"
    },
    {
      "i": 141,
      "title": "中子星最大質量的上限"
    },
    {
      "i": 142,
      "md": "Figure 24.7 顯示，能夠被基態物質的壓力抵抗重力坍縮所支撐的非自轉最大質量約為 $2M_{\\odot}$。中子星的最大質量是天文物理學中的重要數值，因為它被用於觀測上區分黑洞與中子星，如 Section 13.1 所討論。然而，如已提及，Figure 24.7 所示的結果依賴於對超出普通核子密度範圍的物態方程的高難度理論計算，因此超出了地球上許多實驗的檢驗範圍。因此，廣義相對論本身提供中子星最大質量的上限是重要的，它假定詳細知道直至普通核子密度的物態方程，但只對其超出部分做一般性假設。這個上限是本節的主題。我們不試圖推導最佳上限，而是指出其基本原因。"
    },
    {
      "i": 143,
      "md": "最大質量的上限來自相對論性流體靜力平衡方程 (24.13) 以及我們現在說明的幾個關於物態方程的一般假設："
    },
    {
      "i": 144,
      "md": "- 我們假定物質由物態方程 $p = p(\\rho)$ 描述，滿足（1）$\\rho > 0$，（2）$p > 0$，以及（3）$dp / d\\rho > 0$。正能量（1）是物質非常普遍的性質。性質（2）和（3）是物質在微觀上穩定的必要條件。若壓力不為正，或壓力不隨壓縮而增大，那麼在能量上將有利於將任何小體積壓縮到更小，從而導致小尺度上的坍縮。\n\n- 我們假定物態方程在某個基準密度 $\\rho_0$ 以下是已知的。從氦到鈾的核子，其核心密度幾乎相同。這個密度稱為核密度，其值為 $2.9 \\times 10^{-4} \\, \\text{g cm}^3$。在此密度以下，理論計算可以與實際核子相比較，因此對於我們能以一定信心說明基態物質物態方程的密度 $\\rho_0$ 而言，這是一個合理的選擇"
    },
    {
      "i": 145,
      "md": "在這些假設下，我們可以推導最大質量的上限，如下。流體靜力平衡方程 (24.13b) 的右側始終為正。每一項均為正，且 $1 - 2m(r)/r$ 不可能為負，否則 $r$ 內的區域將在黑洞之內。由此可見，壓力隨半徑遞減，由於假設 $dp/d\\rho > 0$，密度也隨半徑遞減。因此，一顆恆星可以分為一個 $\\rho \\geq \\rho_{0}$ 的核心（物態方程在此詳情未知）和一個 $\\rho < \\rho_{0}$ 的外層（物態方程在此已知）。設 $r_{0}$ 為核心半徑，$M_{0}$ 為 $m(r)$ 在該半徑處的值。我們非正式地將 $M_{1}$ 稱為核心質量。由 (24.13a) 我們有"
    },
    {
      "i": 147,
      "md": "因為核心內任意點的密度均大於其表面。因此，"
    },
    {
      "i": 149,
      "md": "另一方面，核心不能位於其自身的 Schwarzschild 半徑以內，否則它將是一個黑洞。因此，"
    },
    {
      "i": 151,
      "md": "這兩個約束 (24.27) 和 (24.28) 如 Figure 24.12 所示。存在一個最大核心質量，為"
    },
    {
      "i": 153,
      "md": "然而，(24.29) 中的上限並不是能做到的最佳上限。若你完成 Problem 19，你將發現對於常密度核心，$2M_0 / r_0$ 的最大值為 $\\frac{8}{9}$，而非 1。僅此一項改進就足以將 (24.29) 中核心質量的 $8M_{\\odot}$ 上限降至 $6.7M_{\\odot}$，仍非最優。總上限質量是核心質量與外層質量之和。外層質量可以通過積分 Section 24.3 中描述的結構方程來求得，但從 $r_0$ 和 $M_0$ 而非中心出發。事實上，核心的最優上限約為 $6.5M_{\\odot}$，在核密度附近的 $\\rho_0$ 值下，外層的貢獻雖小但不可忽略。詳細計算（Hartle 1978）表明，在前述假設下，中子星最大質量的最優廣義相對論上限——核心加外層——為 $6.7M_{\\odot}$，假定物態方程以 Figure 24.6 中總結的形式在 $\\rho_0 = 2.9 \\times 10^{14} \\mathrm{~g/cm}^3$ 以下成立。若進一步限制物態方程，例如聲速小於光速，上限可以降至約 $4M_{\\odot}$。"
    },
    {
      "i": 155,
      "md": "對於不依賴核密度以上物質性質的球形中子星質量上限，正是這一上限給了人們信心，認定 Section 13.1 中討論的雙星 X 射線源中太陽質量量級黑洞的身份認定是可靠的。若從一顆恆星的視向速度和光譜分析雙星軌道，揭示一個質量大於前述上限的緻密 X 射線源，那麼它不可能是中子星，必定是黑洞。"
    }
  ],
  "problems": [
    {
      "num": "10",
      "body": [
        {
          "i": 0,
          "md": "一個 $p = \\rho$ 物態方程的球形物質分佈，被包含在面積為 $4\\pi R^{2}$、質量可忽略的球殼內。（該球殼不由現實物質構成。）"
        },
        {
          "i": 1,
          "md": "(a) 求出流體靜力平衡方程 (24.13) 的一個簡單解，其中壓力和密度的分佈為半徑的負冪次。"
        },
        {
          "i": 2,
          "md": "(b) 這個分佈的總質量是多少？"
        },
        {
          "i": 3,
          "md": "(c) 球殼必須施加多大的壓力？"
        }
      ]
    },
    {
      "num": "11",
      "body": [
        {
          "i": 0,
          "md": "[E, B] 估算基態物質中以下情況對應的密度（g/cm$^{3}$）：典型電子的能量（1）超過典型原子束縛能 \\~ 10 keV，（2）超過電子靜止質量 \\~ .5 MeV，以及（3）超過中子-質子質量差 \\~ 1.3 MeV。"
        }
      ]
    },
    {
      "num": "12",
      "body": [
        {
          "i": 0,
          "md": "[B] 一個電中性的高度相對論性自由電子、質子和中子氣體，通過以下反應維持平衡"
        },
        {
          "i": 2,
          "md": "使得平均沒有電子被吸收，也沒有中子衰變。電子、質子和中子的數密度之間有何關係？"
        }
      ]
    },
    {
      "num": "13",
      "body": [
        {
          "i": 0,
          "md": "[S] 對 (24.7) 和 (24.9) 給出的簡併費米子物態方程，在非相對論和相對論極限下分別求出 (24.18) 所定義的 $\\gamma$。"
        }
      ]
    },
    {
      "num": "14",
      "body": [
        {
          "i": 0,
          "md": "[E] 估算中子星半徑 — 假設自由中子的簡併壓力提供支撐，估算中子星的半徑，然後完成 Problem 12.2。"
        }
      ]
    },
    {
      "num": "15",
      "body": [
        {
          "i": 0,
          "md": "[S] 從波動方程 (24.21) 出發，推導振動弦的正規模頻率和形狀，分別如 (24.22) 和 (24.24) 所示。"
        }
      ]
    },
    {
      "num": "16",
      "body": [
        {
          "i": 0,
          "md": "[S] 求解 Figure 24.7 恆星族質量-半徑關係極值點處各模穩定性的變化。假設頻率平方對中心密度的曲線從不相交。證明穩定性的變化如 Figure 24.11 所示，且只有兩個穩定平衡恆星的範圍。"
        }
      ]
    },
    {
      "num": "17",
      "body": [
        {
          "i": 0,
          "md": "中子星之外的穩定平衡？ — 一位理論家提出了一個新的核密度以上物質物態方程，並想知道它是否可能導致超過中子星和白矮星之外的新型超高密度恆星演化終態。你使用該物態方程和本章的方程，計算了中心密度大於核密度的恆星的質量-半徑關係，如圖所示。曲線在最低密度處代表穩定中子星（NS），但在更高密度時開始螺旋盤繞。假設所示最低密度、最大半徑的恆星是穩定的，是否存在新的穩定平衡族？"
        }
      ]
    },
    {
      "num": "18",
      "body": [
        {
          "i": 0,
          "md": "[E] 利用 Newton 物理，估算自轉週期為 1 s 的中子星表面離心力與重力之比。"
        }
      ]
    },
    {
      "num": "19",
      "body": [
        {
          "i": 0,
          "md": "精化中子星最大質量上限 — 利用 Problem 9 的結果，在 Section 24.6 的記號下，證明核心的質量與半徑必須滿足 $M_{0}/r_{0} < \\frac{4}{9}$。假設 $\\rho_{0}$ 為核密度，求出中心密度高於此值的恆星的核心質量上限"
        }
      ]
    },
    {
      "num": "3",
      "body": [
        {
          "i": 0,
          "md": "玻色子無物態方程 — 繼續前一習題的一維例子，$N$ 個玻色子（不受 Pauli 原理限制的粒子）在長度為 $L$ 的箱中的基態能量是多少？當 $N$ 很大時，$p$ 與 $n$ 之間是否存在獨立於 $N$ 的關係？"
        }
      ]
    },
    {
      "num": "4",
      "body": [
        {
          "i": 0,
          "md": "[A] 從 Einstein 方程推導結構方程 — 利用度規 (24.11) 和完美流體的應力-能量張量 (22.37)，從 Einstein 方程 $G_{\\alpha \\beta} = 8\\pi T_{\\alpha \\hat{\\tau}}$ 以及由此得到的應力-能量局部守恆 $\\nabla_{\\beta}T^{\\alpha \\beta} = 0$，推導三個流體靜力平衡方程 (24.13)。（提示：你可以使用任意組合的方程，但在正交於座標軸的正規基底下，方程 $\\nabla_{\\rho}T_{\\rho}^{*} = 0$、$G_{\\hat{\\tau}\\hat{\\tau}} = 8\\pi T_{\\hat{\\tau}\\hat{\\tau}}$、$G_{\\hat{r}\\hat{r}} = 8\\pi T_{\\hat{r}\\hat{r}}$ 涉及最少的代數運算。度規 (24.11) 的這些 Einstein 張量分量在 Appendix B 中給出。）"
        }
      ]
    },
    {
      "num": "5",
      "body": [
        {
          "i": 0,
          "md": "論證度規"
        },
        {
          "i": 2,
          "md": "其中 $\\alpha$ 是大於 1 的常數，代表圓錐二維表面上的幾何。圓錐的開口角是多少？（評注：這是一個在 $r = 0$ 處不局部平坦的幾何的例子。）"
        }
      ]
    },
    {
      "num": "6",
      "body": [
        {
          "i": 0,
          "md": "[C] 具有固定常數密度 $\\rho$ 的不可壓縮物質與狹義相對論不相容，因為它可以用來以超光速傳送訊號。（如何做到？）但它確實提供了一個相對論性流體靜力平衡的簡單例子。積分結構方程 (24.13a) 和 (24.13b)，求出由 $\\rho$ 為給定常數的物質組成、總質量為 $M$ 的恆星的壓力作為半徑的函數。繪出這些恆星的質量-半徑關係。是否存在最大質量？"
        },
        {
          "i": 1,
          "md": "7. [A] (a) 求出 Problem 6 所求解的球形常密度恆星族內部的度規。仔細討論恆星內部與外部之間的接合條件。\n\n(b) 證明常密度恆星內部 $t = $ 常數曲面的幾何與 Chapter 18 中討論的封閉 FRW 宇宙的均勻空間曲面在局部上相同。\n\n(c) 對於給定的表面積，恆星內部體積是否比在平直空間中更大或更小？"
        }
      ]
    },
    {
      "num": "8",
      "body": [
        {
          "i": 0,
          "md": "利用 Problem 7 的結果，求出並繪製常密度恆星時空幾何中 $t = \\text{const.}$、$\\theta = \\text{const.}$ 二維切片的嵌入圖。"
        }
      ]
    },
    {
      "num": "9",
      "body": [
        {
          "i": 0,
          "md": "[C] (a) 在正文中，我們以中心密度 $\\rho_{c}$ 作為非自轉恆星族的參數，例如 Figure 24.7。但也可以用中心壓力 $p_{c}$ 來參數化。Problem 6 中討論的假想常密度物質組成的恆星，其密度均相同。"
        },
        {
          "i": 1,
          "md": "(b) 對於這些常密度恆星，證明對於每個中心壓力 $p_c$ 的值，存在唯一的質量 $M$ 和半徑 $R$。"
        },
        {
          "i": 2,
          "md": "(c) 在這個常密度 $\\rho$ 的球形恆星族中，從表面觀測到的最大紅移 [參見 (9.20)] 是多少？對應的中心壓力 $p_c$ 是多少？"
        }
      ]
    }
  ]
}